Workbook

Sheet Instructions
A1: IHS AAO MEP BPA PRICING TEMPLATE
A3: Instructions for Completing the MEP BPA Pricing Template
A5: Offerors shall complete the Government-provided pricing template to propose pricing for Mechanical, Electrical, and Plumbing (MEP) services under the BPA.
A7: General Instructions
A8: 1. Complete only the cells shaded in gray. Gray cells indicate contractor input fields. Cells that are not shaded are protected and contain formulas, labels, or Government-provided information and shall not be modified.
A9: 2. All proposed labor rates shall be fully burdened hourly rates, including wages, overhead, profit, insurance, supervision, small tools, and other indirect costs necessary to perform the work.
A10: 3. Labor rates shall apply to work performed during normal working hours unless otherwise specified.
A11: 4. If emergency or after-hours work requires a premium, enter the percentage premium in the designated column. Emergency hourly rates will calculate automatically.
A12: 5. Provide pricing for labor rates, service call or trip charges, emergency mobilization fees, minimum service hours, material markups, and travel rates, if applicable.
A13: 6. Do not delete rows, columns, worksheets, or formulas within this template.
A14: 7. The Government may evaluate pricing using sample call-order scenarios included in this workbook.
A15: 8. If a labor category does not apply to the offeror's organization, enter 0.00 instead of deleting the category.
... A22: Before release, the Government should confirm labor standards applicability, any markup ceilings, and whether travel is reimbursable at proposed rates or limited to GSA rates or actual cost.

Sheet Labor Rates
A1: Tab Instructions
A2: Provide fully burdened hourly labor rates for each labor category listed.
A3: Base Hourly Rate: Enter the fully burdened hourly rate.
A4: Emergency Premium %: Enter the percentage increase for after-hours or emergency work, if applicable.
A5: Emergency Rate: This column calculates automatically.
A6: Comments: Use this field to identify equivalent internal labor categories or clarifying assumptions.
A8: Labor Category | B8: Base Hourly Rate | C8: Emergency Premium % | D8: Emergency Rate | E8: Comments
A9: Master Electrician | D9: =IF(B9="","",B9*(1+C9))
A10: Journeyman Electrician | D10: =IF(B10="","",B10*(1+C10))
A11: Electrical Engineer – Arc Flash | D11: =IF(B11="","",B11*(1+C11))
A12: Arc Flash Technician | D12: =IF(B12="","",B12*(1+C12))
A13: Master Plumber | D13: =IF(B13="","",B13*(1+C13))
A14: Journeyman Plumber | D14: =IF(B14="","",B14*(1+C14))
A15: HVAC Technician | D15: =IF(B15="","",B15*(1+C15))
A16: Mechanical Technician | D16: =IF(B16="","",B16*(1+C16))
A17: Generator Technician | D17: =IF(B17="","",B17*(1+C17))
A18: Emergency Power Specialist (ATS/Generators) | D18: =IF(B18="","",B18*(1+C18))
A19: Load Bank Technician | D19: =IF(B19="","",B19*(1+C19))
A20: Controls Technician (Non‑Proprietary) | D20: =IF(B20="","",B20*(1+C20))
... A24: Project Manager | D24: =IF(B24="","",B24*(1+C24))

Sheet Fees & Minimums
A1: Tab Instructions
A2: Provide flat fees for service calls and emergency mobilization, and minimum billable hours where applicable.
A3: Trip or Service Call Charge – Regular Hours: Flat fee per visit during normal working hours.
A4: Trip or Service Call Charge – After Hours: Flat fee per visit outside normal working hours.
A5: Emergency Mobilization Fee: Additional fee for urgent dispatch requiring immediate response.
A6: Minimum Service Hours: Enter the minimum hours billed per service visit.
A8: Fee Type | B8: Proposed Amount | C8: Unit | D8: Notes
A9: Trip / Service Call – Regular Hours | C9: Flat Fee
A10: Trip / Service Call – After Hours | C10: Flat Fee
A11: Emergency Mobilization Fee | C11: Flat Fee
A12: Minimum Service Hours – Regular | C12: Hours
A13: Minimum Service Hours – Emergency | C13: Hours

Sheet Material Markups
A1: Tab Instructions
A2: Provide proposed markup percentages for the categories listed.
A3: Government Ceiling: Maximum allowable markup established by the Government.
A4: Proposed %: Enter the offeror’s proposed markup percentage.
A5: Compliance: This column checks whether the proposed markup exceeds the Government ceiling.
A6: Markup shall apply to the contractor’s actual acquisition cost unless otherwise stated in the solicitation.
A8: Material Category | B8: Gov Ceiling % | C8: Proposed % | D8: Compliance
A9: Standard Materials | B9: 0.15 | D9: =IF(C9="","",IF(C9<=B9,"OK","EXCEEDS"))
A10: Electrical Components | B10: 0.2 | D10: =IF(C10="","",IF(C10<=B10,"OK","EXCEEDS"))
A11: Mechanical / Generator Components | B11: 0.2 | D11: =IF(C11="","",IF(C11<=B11,"OK","EXCEEDS"))
A12: Plumbing Materials | B12: 0.15 | D12: =IF(C12="","",IF(C12<=B12,"OK","EXCEEDS"))
A13: Emergency Procurement | B13: 0.25 | D13: =IF(C13="","",IF(C613<=B13,"OK","EXCEEDS"))

Sheet Travel
A1: Tab Instructions
A2: Provide proposed travel rates only if travel is separately reimbursable under the solicitation or call order.
A3: Mileage, lodging, per diem, and vehicle rental may be entered where applicable.
A4: Travel reimbursement may be limited by GSA rates, actual cost, or call-order terms.
A6: Travel Item | B6: Proposed Rate | C6: Notes
A7: Mileage ($/mile)
A8: Lodging ($/night if authorized)
A9: Per Diem ($/day if authorized)

Sheet Sample Call Order
A1: Tab Instructions
A2: This worksheet contains Government evaluation scenarios used to compare proposed pricing among offerors.
A3: Do not modify scenario assumptions, labor hours, or formulas in this tab.
A4: Scenario totals may be used for price evaluation purposes.
A6: Government Evaluation Scenario (Do Not Edit Assumptions)
A8: Labor Category | B8: Hours | C8: Rate | D8: Extended
A9: Generator Technician | B9: 6 | C9: =INDEX('Labor Rates'!B9:B24,MATCH(A9,'Labor Rates'!A9:A24,0)) -> 0 | D9: =B9*C9 -> 0
A10: Emergency Power Specialist (ATS/Generators) | B10: 4 | C10: =INDEX('Labor Rates'!B9:B24,MATCH(A10,'Labor Rates'!A9:A24,0)) -> 0 | D10: =B10*C10 -> 0
A11: Journeyman Electrician | B11: 4 | C11: =INDEX('Labor Rates'!B9:B24,MATCH(A11,'Labor Rates'!A9:A24,0)) -> 0 | D11: =B11*C11 -> 0
A13: Trip Charge | C13: ='Fees & Minimums'!B9 -> 0 | D13: =C13 -> 0
A14: Emergency Mobilization | C14: ='Fees & Minimums'!B11 -> 0 | D14: =C14 -> 0
A16: Scenario Total | D16: =SUM(D9:D14) -> 0
