Workbook
Name AcademiaLaborGroups: [1]Constants!$A$21:$A$24
Name GeneralLaborGroups: [1]Constants!$A$27:$A$32
Name IndirectRateCategories: [1]Constants!$A$113:$A$129
Name LaborCollection: [1]Constants!$A$15
Name NoBusinessTypeSelected: [1]Constants!$A$18
Name Offeror.Bus.Type: '[1]Proposer Constants'!$A$4
Name OfferorBusinessTypes: [1]Constants!$A$8:$A$12
Name P1_AWI: '[2]Indirects + AWI'!$L$10
Name Period1_Label: '[1]Proposer Constants'!$B$9
Name Period2_Label: '[1]Proposer Constants'!$C$9
Name Period3_Label: '[1]Proposer Constants'!$D$9
Name Period4_Label: '[1]Proposer Constants'!$E$9
Name Period5_Label: '[1]Proposer Constants'!$F$9
Name Period6_Label: '[1]Proposer Constants'!$G$9
Name SBIRSTTRPhaseChoices: [3]Constants!$A$134:$A$137
Name SBIRSTTRPhaseChoices: [1]Constants!$A$135:$A$138
Name SmallBusinessSizeChoices: [1]Constants!$A$143:$A$146

Sheet Price Breakdown
A1: Price Breakdown
B3: Embedded Entrepreneur Effort (Base) | F3: Minimum Viable Product (Option) | I3: Total Proposed
A6: Labor Category* | B6: Hours | C6: Rate** | D6: Total | F6: Hours | G6: Rate* | H6: Total | I6: Total Price
C7: 0 | D7: =B7*C7 -> 0 | G7: 0 | H7: =F7*G7 -> 0 | I7: =D7+H7 -> 0
C8: 0 | D8: =B8*C8 -> 0 | G8: 0 | H8: =F8*G8 -> 0 | I8: =D8+H8 -> 0
C9: 0 | D9: =B9*C9 -> 0 | G9: 0 | H9: =G9*F9 -> 0 | I9: =D9+H9 -> 0
A10: Labor | B10: =SUM(B7:B9) -> 0 | D10: =SUM(D7:D9) -> 0 | F10: =SUM(F7:F9) -> 0 | H10: =SUM(H7:H9) -> 0 | I10: =D10+H10 -> 0
A12: Travel | D12: =Travel!AC9 -> 0 | H12: =Travel!AC14 -> 0 | I12: =D12+H12 -> 0
A14: Other Direct Costs (ODCs) | D14: ='ODC Details'!E7 -> 0 | H14: ='ODC Details'!E11 -> 0 | I14: =D14+H14 -> 0
A16: Material/Equipment | D16: =Materials!E8+Equipment!I6 -> 0 | H16: =Materials!E13+Equipment!I9 -> 0 | I16: =D16+H16 -> 0
A18: Profit | C18: 0 | D18: =C18*SUM(D10:D16) -> 0 | G18: 0 | H18: =G18*SUM(H10:H16) -> 0 | I18: =H18+D18 -> 0
A20: Total Price | D20: =SUM(D10:D18) -> 0 | H20: =SUM(H10:H18) -> 0 | I20: =SUM(D20:H20) -> 0
A23: *Offeror may add rows as required
A24: **Fully Burdened Rate - Inclusive of all direct and indirect labor costs.

Sheet Travel
A1: TRAVEL | B1: (Notes 1, 2 and 3) | C1: =[1]General!C2 -> 0
C3: TRAVEL DETAIL
A4: Base / Option / Task | B4: Purpose of Trip | C4: Origin Destination | D4: Final Destination | E4: # People | F4: # Days | G4: # of Trips | H4: # days at 100% Hotel per diem | I4: # days at 100% M&IE per diem | J4: # days at 75% M&IE per diem | K4: Round Trip Airfare/ Trainfare per person | L4: Total Airfare/ Trainfare $ per Trip | M4: Hotel Per Diem Rate per person | N4: Total Hotel Per Diem $ per trip | O4: M&IE Per Diem Rate per person | P4: 100% M&IE Per Diem $ | Q4: 75% M&IE Per Diem $ | R4: Total M&IE Per Diem $ per trip | S4: Car Rental dollars per day including Taxes & Fees | T4: # of Cars (1-3 people per car) | U4: Total Car rental $ per trip | V4: Standard Personal Car Mileage Rate | W4: Estimated Number of Round trip Miles per Car | X4: # of Personal Cars | Y4: Total Mileage Rate Dollars | Z4: Conference Fees | AA4: Other Expenses (tolls, parking, rental gas, wi-fi) | AB4: TOTAL DIRECT DOLLARS PER TRIP | AC4: GRAND TOTAL DIRECT DOLLARS FOR ALL TRIPS
H5: =IF((F5>0),F5-1,0) -> 0 | I5: =IF(F5>2,F5-2,0) -> 0 | J5: =IF(F5<=2,F5,F5-I5) -> 0 | L5: =+K5*E5 -> 0 | N5: =M5*E5*H5 -> 0 | P5: =+O5*E5*I5 -> 0 | Q5: =(+O5*E5*J5)*0.75 -> 0 | R5: =SUM(P5:Q5) -> 0 | U5: =T5*S5*H5 -> 0 | Y5: =W5*V5*X5 -> 0 | AB5: =+Y5+U5+R5+N5+L5+Z5+AA5 -> 0 | AC5: =+AB5*G5 -> 0
H6: =IF((F6>0),F6-1,0) -> 0 | I6: =IF(F6>2,F6-2,0) -> 0 | J6: =IF(F6<=2,F6,F6-I6) -> 0 | L6: =+K6*E6 -> 0 | N6: =M6*E6*H6 -> 0 | P6: =+O6*E6*I6 -> 0 | Q6: =(+O6*E6*J6)*0.75 -> 0 | R6: =SUM(P6:Q6) -> 0 | U6: =T6*S6*H6 -> 0 | Y6: =W6*V6*X6 -> 0 | AB6: =+Y6+U6+R6+N6+L6+Z6+AA6 -> 0 | AC6: =+AB6*G6 -> 0
H7: =IF((F7>0),F7-1,0) -> 0 | I7: =IF(F7>2,F7-2,0) -> 0 | J7: =IF(F7<=2,F7,F7-I7) -> 0 | L7: =+K7*E7 -> 0 | N7: =M7*E7*H7 -> 0 | P7: =+O7*E7*I7 -> 0 | Q7: =(+O7*E7*J7)*0.75 -> 0 | R7: =SUM(P7:Q7) -> 0 | U7: =T7*S7*H7 -> 0 | Y7: =W7*V7*X7 -> 0 | AB7: =+Y7+U7+R7+N7+L7+Z7+AA7 -> 0 | AC7: =+AB7*G7 -> 0
H8: =IF((F8>0),F8-1,0) -> 0 | I8: =IF(F8>2,F8-2,0) -> 0 | J8: =IF(F8<=2,F8,F8-I8) -> 0 | L8: =+K8*E8 -> 0 | N8: =M8*E8*H8 -> 0 | P8: =+O8*E8*I8 -> 0 | Q8: =(+O8*E8*J8)*0.75 -> 0 | R8: =SUM(P8:Q8) -> 0 | U8: =T8*S8*H8 -> 0 | Y8: =W8*V8*X8 -> 0 | AB8: =+Y8+U8+R8+N8+L8+Z8+AA8 -> 0 | AC8: =+AB8*G8 -> 0
A9: Base Total Travel | AC9: =SUM(AC5:AC8) -> 0
H10: =IF((F10>0),F10-1,0) -> 0 | I10: =IF(F10>2,F10-2,0) -> 0 | J10: =IF(F10<=2,F10,F10-I10) -> 0 | L10: =+K10*E10 -> 0 | N10: =M10*E10*H10 -> 0 | P10: =+O10*E10*I10 -> 0 | Q10: =(+O10*E10*J10)*0.75 -> 0 | R10: =SUM(P10:Q10) -> 0 | U10: =T10*S10*H10 -> 0 | Y10: =W10*V10*X10 -> 0 | AB10: =+Y10+U10+R10+N10+L10+Z10+AA10 -> 0 | AC10: =+AB10*G10 -> 0
H11: =IF((F11>0),F11-1,0) -> 0 | I11: =IF(F11>2,F11-2,0) -> 0 | J11: =IF(F11<=2,F11,F11-I11) -> 0 | L11: =+K11*E11 -> 0 | N11: =M11*E11*H11 -> 0 | P11: =+O11*E11*I11 -> 0 | Q11: =(+O11*E11*J11)*0.75 -> 0 | R11: =SUM(P11:Q11) -> 0 | U11: =T11*S11*H11 -> 0 | Y11: =W11*V11*X11 -> 0 | AB11: =+Y11+U11+R11+N11+L11+Z11+AA11 -> 0 | AC11: =+AB11*G11 -> 0
H12: =IF((F12>0),F12-1,0) -> 0 | I12: =IF(F12>2,F12-2,0) -> 0 | J12: =IF(F12<=2,F12,F12-I12) -> 0 | L12: =+K12*E12 -> 0 | N12: =M12*E12*H12 -> 0 | P12: =+O12*E12*I12 -> 0 | Q12: =(+O12*E12*J12)*0.75 -> 0 | R12: =SUM(P12:Q12) -> 0 | U12: =T12*S12*H12 -> 0 | Y12: =W12*V12*X12 -> 0 | AB12: =+Y12+U12+R12+N12+L12+Z12+AA12 -> 0 | AC12: =+AB12*G12 -> 0
H13: =IF((F13>0),F13-1,0) -> 0 | I13: =IF(F13>2,F13-2,0) -> 0 | J13: =IF(F13<=2,F13,F13-I13) -> 0 | L13: =+K13*E13 -> 0 | N13: =M13*E13*H13 -> 0 | P13: =+O13*E13*I13 -> 0 | Q13: =(+O13*E13*J13)*0.75 -> 0 | R13: =SUM(P13:Q13) -> 0 | U13: =T13*S13*H13 -> 0 | Y13: =W13*V13*X13 -> 0 | AB13: =+Y13+U13+R13+N13+L13+Z13+AA13 -> 0 | AC13: =+AB13*G13 -> 0
A14: Option Total Travel | AC14: =SUM(AC10:AC13) -> 0
A15: GRAND TOTAL TRAVEL | AC15: =AC9+AC14 -> 0
A18: Instructions: | B18: • When completing the “Origin” and “Final” Destination information, enter the city and state where travel will originate and end. For example, from Seattle WA to Washington DC. Do not list airport codes. • Include the trip purpose. It must be referred to in the Technical Proposal. Publications, conference attendance, and presentations are encouraged but must be justified to and approved by the Program Officer. • Remember that you cannot stay overnight the same number of days that you travel. There must always be one more day than night. • The first day and the last day of travel are charged at 75% of the M&IE per diem rate. If you travel for just one day (lasting 12 hours or more), the M&IE per diem rate is also charged at 75%. For answers to FAQs about per diem and travel rates, please review: https://www.gsa.gov/travel/plan-book/per-diem-rates/frequently-asked-questions-per-diem. • Do not combine any categories. • For lodging and M&IE, use federal Per Diem Rates found at https://www.gsa.gov. • Submit backup for airfare and rental cars. Price airfare at economy rates; indicate if the airfare is refundable.
A20: Note 1: | B20: Estimates and the resultant costs claimed must conform to the applicable Federal cost principles.
R22: • Do not combine any categories.
A24: Note 2: | B24: Include a separate section in the above table for the base and each option
A26: Note 3: | B26: If there are miscellaneous expenses associated with the trip, provide description and rationale.

Sheet ODC Details
A1: OTHER DIRECT COSTS (Note 1) | D1: =[1]General!C2 -> 0
A3: Description (Note 2) | B3: Qty | C3: Unit of Issue | D3: Unit Price | E3: Total Price | F3: Basis of Estimate (Note 3) | G3: Supporting documentation has been provided (Y/N) (Note 3) | H3: Reference Document Number
A4: Base | E4: =B4*D4 -> 0 | I4: Y
E5: =B5*D5 -> 0 | I5: N
E6: =B6*D6 -> 0
A7: Base Total | E7: =SUM(E4:E6) -> 0
A8: Option | E8: =B8*D8 -> 0
E9: =B9*D9 -> 0
E10: =B10*D10 -> 0
A11: Option Total | E11: =SUM(E8:E10) -> 0
D12: TOTAL | E12: =E7+E11 -> 0
A15: Instructions: | B15: • Indicate “Not Applicable” in cell B4 if there is no information to include for the Base and in cell B7 if there is no information to include for the Option. • If you have any ODC entries, be sure to fill out all columns. • Include supporting documentation for each entry with unit cost over $5,000. Backup may consist of a vendor quote, past purchase order/invoice, information from a website, or a detailed explanation of labor and material costs for custom made items. • Label ODC backup clearly with a Reference Document Number in the format of ODC000 starting with ODC001. Place the Reference Document Number in the upper right hand side of the backup page. If there are several quotes on a page, make sure each desired item has a separate reference number placed to the left of the item on the backup page. The Reference Document Number must be listed next to the appropriate item on the ODC worksheet under the Reference Document Number column. • Ensure that descriptions and vendors listed on the ODC Details worksheet match information provided in the backup. • Number Reference Document Numbers sequentially so they match the Item number in the Base. For example, Item number 1 should match ODC001. If the same items are used again in the options, there is no need to renumber or add additional copies of the backup, but list the items sequentially by Reference Document Number. As an example, ODC002 could be used for Base item number 2, Option I item number 1 and Option II Item number 1.
A17: Note 1: | B17: Examples include rental fees, shipping costs, license fees
A19: Note 2: | B19: Include a separate section in the above table for the Base and Option.
A21: Note 3: | B21: In an attachment, provide all supporting documentation to support your price basis, e.g. copy of quote, page from catalog, or method used for deriving engineering estimates.

Sheet Materials
A1: MATERIALS (Note 1) | D1: =[1]General!C2 -> 0
A3: Item (Note 2) | B3: Description of Material | C3: Qty | D3: Unit Price | E3: Total Price | F3: Competitive /Sole Source | G3: Vendor/Source (If known) | H3: Basis of Estimate (Note 3) | I3: Supporting documentation has been provided (Y/N) (Note 3) | J3: Reference Document Number
A4: Base | E4: =C4*D4 -> 0 | K4: Y
A5: 1 | E5: =C5*D5 -> 0 | K5: N
A6: 2 | E6: =C6*D6 -> 0
A7: 3 | E7: =C7*D7 -> 0
A8: Base Total | E8: =SUM(E4:E7) -> 0
A9: Option | E9: =C9*D9 -> 0
A10: 4 | E10: =C10*D10 -> 0
A11: 5 | E11: =C11*D11 -> 0
A12: 6 | E12: =C12*D12 -> 0
A13: Option Total | E13: =SUM(E9:E12) -> 0
D14: TOTAL | E14: =E8+E13 -> 0
A17: Instructions: | B17: • Indicate “Not Applicable” in cell B4 if there is no information to include for the Base and in cell B8 if there is no information to include for the Option. • Fill out all columns on the Materials/Supplies Tab for each item. • Add additional lines if needed. • Include supporting documentation for each entry with unit cost over $5,000. Backup may consist of a vendor quote, past purchase order/invoice, information from a website, or a detailed explanation of labor and material costs for custom made items. • Clearly label Materials/Supplies backup with a Reference Document Number in the format of MAT000 starting with MAT001. Place the Reference Document Number in the upper right hand side of the backup page. If there are several quotes on a page, items not desired must be lined out and each desired item must have a separate reference number placed to the left of the item on the backup page. The Reference Document Number must be listed next to the appropriate item on the Materials/Supplies worksheet under the Reference Document Number column. • Ensure that descriptions and vendors listed on the Materials/Supplies worksheet match information provided in the backup. • Number Reference Document Numbers sequentially so they match the Item number in the Base. For example, Item number 1 should match MAT001. If the same items are used again in the options, there is no need to renumber or add additional copies of the backup, but list the items sequentially for each option by Reference Document Number. As an example, MAT010 could be used for Base item number 10 and Option I item number1.
A19: Note 1: | B19: Material is property that may be incorporated into or attached to a deliverable end item or that may be consumed or expended in performing a contract. It includes assemblies, components, parts, raw and processed materials, and small tools and supplies that may be consumed in normal use in performing a contract. Material should be proposed separately from Equipment (see following spreadsheet and definitions).
A21: Note 2: | B21: Include a separate section in the above table for the Base and each Option. Add additional lines labeled with Options if needed.
A23: Note 3: | B23: In an attachment, provide all supporting documentation to support your price basis, e.g. copy of vendor quote, past invoice/PO, page from catalog, or method used for deriving engineering estimates.

Sheet Equipment
A1: EQUIPMENT (Note 1) | C1: =[1]General!C2 -> 0
A3: Item (Note 2) | B3: Description of Equipment (Note 1) | C3: Justification for why the equipment is needed | D3: Will the equipment be included as part of a deliverable item under the award? (Y/N) | E3: Type of Equipment (special test equipment, special tooling, general purpose equipment, or plant equipment) (Note 3) | F3: Qty | G3: Unit of Issue | H3: Unit Price | I3: Total Price | J3: Vendor/Source | K3: Basis of Estimate (Note 4) | L3: Supporting documentation has been provided (Y/N) (Note 4) | M3: Reference Document Number
A4: Base | I4: =F4*H4 -> 0 | N4: Y
I5: =F5*H5 -> 0 | N5: N
A6: Base Total | I6: =SUM(I4:I5) -> 0
A7: Option
A9: Option Total | I9: =SUM(I7:I8) -> 0
H10: TOTAL | I10: =I6+I9 -> 0
A12: Instructions: | B12: • Indicate “Not Applicable” in cell B4 if there is no information to include for the Base and in cell B7 if there is no information to include for the Option. • Fill out all columns on the Equipment Tab for each item. • Add additional lines if needed. • Provide justification for equipment. Be sure to indicate the benefit(s) to the Government. Expand on any statements along the lines of “It is needed to support the project deliverables”. Costs must be approved by the Program Officer. Link the justification to the type of equipment purchase, i.e. special test equipment, special tooling, or plant equipment. • Include supporting documentation for each entry with unit cost over $5,000. Backup may consist of a vendor quote, past purchase order or invoice, information from a website, or a detailed explanation of labor and material costs for custom made items. • Label equipment backup clearly with a Reference Document Number in the format of EQ000 starting with EQ001. Place the Reference Document Number in the upper right hand side of the backup page. If there are several quotes on a page, items not desired must be lined out and each desired item must have a separate reference number placed to the left of the item on the backup page. The Reference Document Number must be listed next to the appropriate item on the Equipment worksheet under the Reference Document Number column. • Ensure that descriptions and vendors listed on the Equipment worksheet match information provided in the backup. • Number Reference Document Numbers sequentially so they match the Item number in the Base. For example, Item number 1 should match EQ001. If the same items are used again in the options, there is no need to renumber or add additional copies of the backup, but list the items sequentially for each option by Reference Document Number. As an example, EQ010 could be used for Base item number 10, Option I item number 1 and Option II Item number 6.
A14: Note 1: | B14: Contractors are normally required to furnish all equipment and/or facilities necessary to perform Government contracts (see FAR 45.102(a)). The Government may allow equipment and/or facilities only under special circumstances. If equipment and/or facilities are proposed, the specific description should identify the component, nomenclature, and configuration of the equipment/hardware that it proposes to purchase for this effort. The purchase on a direct reimbursement basis of equipment that is not included in a deliverable item will be evaluated for allowability on a case-by-case basis. Maximum use of Government integration, test, and experiment facilities is encouraged.
A17: Note 2: | B17: Include a separate section in the above table for the Base and each Option. Add additional lines labeled with Options if needed.
A19: Note 3: | B19: Definitions:
B20: Special Test Equipment is defined as either single or multipurpose integrated test units engineered, designed, fabricated, or modified to accomplish special purpose testing in performing a contract. It consists of items or assemblies of equipment including standard or general purpose items or components that are interconnected and interdependent so as to become a new functional entity for special testing purposes.
B23: Special tooling is defined as jigs, dies, fixtures, molds, patterns, taps, gauges, and all components of these items, including foundations and similar improvements necessary for installing special test equipment, and which are of such a specialized nature that without substantial modification or alteration their use is limited to the development or production of particular supplies or parts thereof or to the performance of particular services.
B27: Plant equipment means personal property of a capital nature (including equipment, machine tools, test equipment, furniture, vehicles, and accessory and auxiliary items) for use in manufacturing supplies, in performing services, or for any administrative or general plant purpose. It does not include special tooling or special test equipment.
A30: Note 4: | B30: In an attachment, provide all supporting documentation to support your price basis, e.g. copy of vendor quote, past invoice/PO, page from catalog, or method used for deriving engineering estimates.
