Workbook

Sheet Subcontractor Instructions
A1: INSTRUCTIONS TO SUBCONTRACTORS
A3: General
A4: 1 | B4: The subcontractor shall complete this Government Format Pricing Model (GFPM-Subs).
A5: 2 | B5: All proposed direct labor rates shall be in line with justifying data (historical/incurred costs, salary survey, BLS OES etc.) for each identified locality.
A6: 3 | B6: The subcontractor GFPM will be utilized for each subcontractor to show its compliance with providing a full labor buildup, per labor category and to ensure compliance with the Government provided floor rates.
A7: "Subcontractor Labor Build" Tab
A8: 1 | B8: All subcontractors must provide the subcontractor GFPM to the prime offeror for submittal to the Government as part of the prime offeror proposal OR each subcontractor must submit this file directly to the Government.
A9: 2 | B9: Offeror input is required in all applicable cells highlighted in yellow.
A10: 3 | B10: The "Labor Categories & Hours" table (columns A - F) contain all of the performance locations and labor categories that the USG anticipates to be necessary for completion of this effort. Offerors shall input the proposed number of hours in column F that will be completed by the subcontractor for each applicable labor category being performed by the subcontractor.
A11: 4 | B11: In the "Subcontractor Labor Build" table (columns H-T), subcontractors are required to submit fully burdened labor rates for each of the labor categories that the subcontractor is performing (Column Q). Subcontractors shall insert all of the cost elements (direct labor, fringe benefit costs, labor overhead costs, general & administrative cost, profit/fee etc.) that make up all of the fully burdened labor rates proposed (Columns I - P). If necessary, subcontractors may submit additional cost data in it's own format to further justify the proposed single elements of the prime labor costs.
A12: 5 | B12: Offerors shall insert direct labor rates in Ordering Period 1 for the applicable labor categories (I5 - I28) and and in Ordering Period 4 for the applicable labor categories (I108 - I115). Note: Per section L of the RFP, the proposed direct labor rates must meet or exceed the USG floor rates referenced in Ordering Period 1 (H5 - H28) and in Ordering Period 4 (H108 - H115).
A13: 6 | B13: In the event a subcontractor proposes a direct labor rate below the floor rate in error, the subcontractor GFPM corrects this error by utilizing the floor rate (as calculated by the pre-populated formula in column J) to compute the subcontractor costs that contribute to the subcontractor proposed FBLR in columns K - P.
A14: 7 | B14: Profit / fee formulas in column P restrict subcontractors from proposing negative profit/fee percentages.
A15: 8 | B15: Particular cells are locked and cannot be edited. Cells highlighted in yellow can be modified to fit a subcontractors accounting methods, however, the Government has included pre-populated formulas if applicable.
A16: 9 | B16: The FBLR proposed in column Q should be consistent with the FBLR provided to the prime for the primes submittal of its proposal.
A17: "Escalation" Tab
A18: 1 | B18: This tab provides the data for the labor escalation rates which apply to all option periods of performance tabs.
A19: 2 | B19: Per section L of the RFP, for evaluation purposes only, this solicitation has set a minimum escalation for each period of performance. Subcontractors may choose to increase this rate in column C of the escalation tab, but shall not propose an escalation rate which is below the USG minimum.
A20: "DBA Insurance" Tab
A21: 1 | B21: Subcontractors shall demonstrate on the DBA Tab of the GFPM-Subs how the estimated DBA Insurance Amount was calculated, if applicable.
A22: 2 | B22: DBA Insurance shall not be included in any FBLRs and may not have indirect expense or fee added to it.
A23: 3 | B23: Subcontractors shall provide a copy of the DBA Insurance quote, if applicable.
A24: "Sub FBLR & DBA Summary" Tab
A25: 1 | B25: To promote consistency between subcontractor files and prime offeror files, the Government has provided a FBLR & DBA Summary tab within the Subcontractor GFPM for the subcontractor to be able to more easily transfer its proposed FBLRs and DBA Insurance cost totals for each option period, to the prime offeror for the prime offeror to include in its proposal.
A26: 2 | B26: The Hours and FBLRs (columns F & G) are automatically populated in this tab as they are pulled directly from the 'Subcontractor Labor Build' tab.
A27: 3 | B27: The DBA Insurance costs must be manually input by the Subcontractors into the yellow cells, if applicable.

Sheet Subcontractor Labor Build
A1: Ordering Period 1:
A2: Ordering Period 1 Labor Categories & Hours
A3: Service | B3: ID | C3: Labor Category | D3: Reference | E3: Location | F3: Hours | H3: (Floor Rate) | I3: Direct Labor (Proposed) | J3: Direct Labor (Calculation) | K3: Fringe Benefit | L3: Labor OH 1 | M3: G&A | N3: FCCOM | O3: Cost | P3: Fee | Q3: FBLR | R3: Total Cost | S3: Total Fee | T3: Total Price
A4: CONUS
A5: Program Management | B5: 001 | C5: Project Management Specialist | D5: Section H.3.1.11 | E5: CONUS | H5: 42.46 | J5: =IF($I5<$H5,$H5,$I5) -> 42.46 | K5: =(J5*$K$4) -> 0 | L5: =(K5+J5)*$L$4 -> 0 | M5: =(K5+J5+L5)*$M$4 -> 0 | N5: =(J5+K5+L5+M5)*$N$4 -> 0 | O5: =SUM(J5:N5) -> 42.46 | P5: =IF($P$4<0,"N/A",$P$4*(J5+K5+L5+M5)) -> 0 | Q5: =SUM(O5:P5) -> 42.46 | R5: =O5*F5 -> 0 | S5: =P5*F5 -> 0 | T5: =Q5*F5 -> 0
A6: Field Service Representative (FSR) | B6: 002 | C6: Field Service Representative | D6: Section H.3.1.9 | E6: CONUS | H6: 29.76 | J6: =IF($I6<$H6,$H6,$I6) -> 29.76 | K6: =(J6*$K$4) -> 0 | L6: =(K6+J6)*$L$4 -> 0 | M6: =(K6+J6+L6)*$M$4 -> 0 | N6: =(J6+K6+L6+M6)*$N$4 -> 0 | O6: =SUM(J6:N6) -> 29.76 | P6: =IF($P$4<0,"N/A",$P$4*(J6+K6+L6+M6)) -> 0 | Q6: =SUM(O6:P6) -> 29.76 | R6: =O6*F6 -> 0 | S6: =P6*F6 -> 0 | T6: =Q6*F6 -> 0
A7: General Maintenance | B7: 003 | C7: Heavy Equipment Mechanic | D7: Section H.3.1.3 | E7: CONUS | H7: 29.76 | J7: =IF($I7<$H7,$H7,$I7) -> 29.76 | K7: =(J7*$K$4) -> 0 | L7: =(K7+J7)*$L$4 -> 0 | M7: =(K7+J7+L7)*$M$4 -> 0 | N7: =(J7+K7+L7+M7)*$N$4 -> 0 | O7: =SUM(J7:N7) -> 29.76 | P7: =IF($P$4<0,"N/A",$P$4*(J7+K7+L7+M7)) -> 0 | Q7: =SUM(O7:P7) -> 29.76 | R7: =O7*F7 -> 0 | S7: =P7*F7 -> 0 | T7: =Q7*F7 -> 0
A8: Modified Work Orders (MWO) | B8: 004 | C8: Field Service Representative | D8: Section H.3.1.9 | E8: CONUS | H8: 29.76 | J8: =IF($I8<$H8,$H8,$I8) -> 29.76 | K8: =(J8*$K$4) -> 0 | L8: =(K8+J8)*$L$4 -> 0 | M8: =(K8+J8+L8)*$M$4 -> 0 | N8: =(J8+K8+L8+M8)*$N$4 -> 0 | O8: =SUM(J8:N8) -> 29.76 | P8: =IF($P$4<0,"N/A",$P$4*(J8+K8+L8+M8)) -> 0 | Q8: =SUM(O8:P8) -> 29.76 | R8: =O8*F8 -> 0 | S8: =P8*F8 -> 0 | T8: =Q8*F8 -> 0
B9: 005 | C9: Modified Work Orders (MWO) | D9: Section H.3.1.6 | E9: CONUS | H9: 29.76 | J9: =IF($I9<$H9,$H9,$I9) -> 29.76 | K9: =(J9*$K$4) -> 0 | L9: =(K9+J9)*$L$4 -> 0 | M9: =(K9+J9+L9)*$M$4 -> 0 | N9: =(J9+K9+L9+M9)*$N$4 -> 0 | O9: =SUM(J9:N9) -> 29.76 | P9: =IF($P$4<0,"N/A",$P$4*(J9+K9+L9+M9)) -> 0 | Q9: =SUM(O9:P9) -> 29.76 | R9: =O9*F9 -> 0 | S9: =P9*F9 -> 0 | T9: =Q9*F9 -> 0
B10: 006 | C10: Quality Assurance | D10: Section H.3.1.10 | E10: CONUS | H10: 29.76 | J10: =IF($I10<$H10,$H10,$I10) -> 29.76 | K10: =(J10*$K$4) -> 0 | L10: =(K10+J10)*$L$4 -> 0 | M10: =(K10+J10+L10)*$M$4 -> 0 | N10: =(J10+K10+L10+M10)*$N$4 -> 0 | O10: =SUM(J10:N10) -> 29.76 | P10: =IF($P$4<0,"N/A",$P$4*(J10+K10+L10+M10)) -> 0 | Q10: =SUM(O10:P10) -> 29.76 | R10: =O10*F10 -> 0 | S10: =P10*F10 -> 0 | T10: =Q10*F10 -> 0
B11: 007 | C11: Software | D11: Section H.3.1.5 | E11: CONUS | H11: 29.76 | J11: =IF($I11<$H11,$H11,$I11) -> 29.76 | K11: =(J11*$K$4) -> 0 | L11: =(K11+J11)*$L$4 -> 0 | M11: =(K11+J11+L11)*$M$4 -> 0 | N11: =(J11+K11+L11+M11)*$N$4 -> 0 | O11: =SUM(J11:N11) -> 29.76 | P11: =IF($P$4<0,"N/A",$P$4*(J11+K11+L11+M11)) -> 0 | Q11: =SUM(O11:P11) -> 29.76 | R11: =O11*F11 -> 0 | S11: =P11*F11 -> 0 | T11: =Q11*F11 -> 0
B12: 008 | C12: Welder | D12: Section H.3.1.4 | E12: CONUS | H12: 23.57 | J12: =IF($I12<$H12,$H12,$I12) -> 23.57 | K12: =(J12*$K$4) -> 0 | L12: =(K12+J12)*$L$4 -> 0 | M12: =(K12+J12+L12)*$M$4 -> 0 | N12: =(J12+K12+L12+M12)*$N$4 -> 0 | O12: =SUM(J12:N12) -> 23.57 | P12: =IF($P$4<0,"N/A",$P$4*(J12+K12+L12+M12)) -> 0 | Q12: =SUM(O12:P12) -> 23.57 | R12: =O12*F12 -> 0 | S12: =P12*F12 -> 0 | T12: =Q12*F12 -> 0
A13: New Equipment Training (NET) | B13: 009 | C13: Instructor Supervisor | D13: Section H.3.1.7 | E13: CONUS | H13: 25.3 | J13: =IF($I13<$H13,$H13,$I13) -> 25.3 | K13: =(J13*$K$4) -> 0 | L13: =(K13+J13)*$L$4 -> 0 | M13: =(K13+J13+L13)*$M$4 -> 0 | N13: =(J13+K13+L13+M13)*$N$4 -> 0 | O13: =SUM(J13:N13) -> 25.3 | P13: =IF($P$4<0,"N/A",$P$4*(J13+K13+L13+M13)) -> 0 | Q13: =SUM(O13:P13) -> 25.3 | R13: =O13*F13 -> 0 | S13: =P13*F13 -> 0 | T13: =Q13*F13 -> 0
B14: 010 | C14: Instructor | D14: Section H.3.1.8 | E14: CONUS | H14: 25.3 | J14: =IF($I14<$H14,$H14,$I14) -> 25.3 | K14: =(J14*$K$4) -> 0 | L14: =(K14+J14)*$L$4 -> 0 | M14: =(K14+J14+L14)*$M$4 -> 0 | N14: =(J14+K14+L14+M14)*$N$4 -> 0 | O14: =SUM(J14:N14) -> 25.3 | P14: =IF($P$4<0,"N/A",$P$4*(J14+K14+L14+M14)) -> 0 | Q14: =SUM(O14:P14) -> 25.3 | R14: =O14*F14 -> 0 | S14: =P14*F14 -> 0 | T14: =Q14*F14 -> 0
A15: Total Package Fielding (TPF) and De-processing | B15: 011 | C15: Heavy Equipment Mechanic | D15: Section H.3.1.3 | E15: CONUS | H15: 29.76 | J15: =IF($I15<$H15,$H15,$I15) -> 29.76 | K15: =(J15*$K$4) -> 0 | L15: =(K15+J15)*$L$4 -> 0 | M15: =(K15+J15+L15)*$M$4 -> 0 | N15: =(J15+K15+L15+M15)*$N$4 -> 0 | O15: =SUM(J15:N15) -> 29.76 | P15: =IF($P$4<0,"N/A",$P$4*(J15+K15+L15+M15)) -> 0 | Q15: =SUM(O15:P15) -> 29.76 | R15: =O15*F15 -> 0 | S15: =P15*F15 -> 0 | T15: =Q15*F15 -> 0
B16: 012 | C16: Material Handling Specialist | D16: Section H.3.1.2 | E16: CONUS | H16: 25.91 | J16: =IF($I16<$H16,$H16,$I16) -> 25.91 | K16: =(J16*$K$4) -> 0 | L16: =(K16+J16)*$L$4 -> 0 | M16: =(K16+J16+L16)*$M$4 -> 0 | N16: =(J16+K16+L16+M16)*$N$4 -> 0 | O16: =SUM(J16:N16) -> 25.91 | P16: =IF($P$4<0,"N/A",$P$4*(J16+K16+L16+M16)) -> 0 | Q16: =SUM(O16:P16) -> 25.91 | R16: =O16*F16 -> 0 | S16: =P16*F16 -> 0 | T16: =Q16*F16 -> 0
B17: 013 | C17: Quality Assurance | D17: Section H.3.1.10 | E17: CONUS | H17: 29.76 | J17: =IF($I17<$H17,$H17,$I17) -> 29.76 | K17: =(J17*$K$4) -> 0 | L17: =(K17+J17)*$L$4 -> 0 | M17: =(K17+J17+L17)*$M$4 -> 0 | N17: =(J17+K17+L17+M17)*$N$4 -> 0 | O17: =SUM(J17:N17) -> 29.76 | P17: =IF($P$4<0,"N/A",$P$4*(J17+K17+L17+M17)) -> 0 | Q17: =SUM(O17:P17) -> 29.76 | R17: =O17*F17 -> 0 | S17: =P17*F17 -> 0 | T17: =Q17*F17 -> 0
B18: 014 | C18: Supply/Procurement Specialist | D18: Section H.3.1.1 | E18: CONUS | H18: 33.8 | J18: =IF($I18<$H18,$H18,$I18) -> 33.8 | K18: =(J18*$K$4) -> 0 | L18: =(K18+J18)*$L$4 -> 0 | M18: =(K18+J18+L18)*$M$4 -> 0 | N18: =(J18+K18+L18+M18)*$N$4 -> 0 | O18: =SUM(J18:N18) -> 33.8 | P18: =IF($P$4<0,"N/A",$P$4*(J18+K18+L18+M18)) -> 0 | Q18: =SUM(O18:P18) -> 33.8 | R18: =O18*F18 -> 0 | S18: =P18*F18 -> 0 | T18: =Q18*F18 -> 0
B19: 015 | C19: Welder | D19: Section H.3.1.4 | E19: CONUS | H19: 23.57 | J19: =IF($I19<$H19,$H19,$I19) -> 23.57 | K19: =(J19*$K$4) -> 0 | L19: =(K19+J19)*$L$4 -> 0 | M19: =(K19+J19+L19)*$M$4 -> 0 | N19: =(J19+K19+L19+M19)*$N$4 -> 0 | O19: =SUM(J19:N19) -> 23.57 | P19: =IF($P$4<0,"N/A",$P$4*(J19+K19+L19+M19)) -> 0 | Q19: =SUM(O19:P19) -> 23.57 | R19: =O19*F19 -> 0 | S19: =P19*F19 -> 0 | T19: =Q19*F19 -> 0
A20: OCONUS
A21: Field Service Representative (FSR) | B21: 016 | C21: Field Service Representative | E21: OCONUS | H21: 31.25 | J21: =IF($I21<$H21,$H21,$I21) -> 31.25 | K21: =(J21*$K$4) -> 0 | L21: =(K21+J21)*$L$4 -> 0 | M21: =(K21+J21+L21)*$M$4 -> 0 | N21: =(J21+K21+L21+M21)*$N$4 -> 0 | O21: =SUM(J21:N21) -> 31.25 | P21: =IF($P$4<0,"N/A",$P$4*(J21+K21+L21+M21)) -> 0 | Q21: =SUM(O21:P21) -> 31.25 | R21: =O21*F21 -> 0 | S21: =P21*F21 -> 0 | T21: =Q21*F21 -> 0
A22: General Maintenance | B22: 017 | C22: Heavy Equipment Mechanic | E22: OCONUS | H22: 31.25 | J22: =IF($I22<$H22,$H22,$I22) -> 31.25 | K22: =(J22*$K$4) -> 0 | L22: =(K22+J22)*$L$4 -> 0 | M22: =(K22+J22+L22)*$M$4 -> 0 | N22: =(J22+K22+L22+M22)*$N$4 -> 0 | O22: =SUM(J22:N22) -> 31.25 | P22: =IF($P$4<0,"N/A",$P$4*(J22+K22+L22+M22)) -> 0 | Q22: =SUM(O22:P22) -> 31.25 | R22: =O22*F22 -> 0 | S22: =P22*F22 -> 0 | T22: =Q22*F22 -> 0
A23: New Equipment Training (NET) | B23: 018 | C23: Instructor Supervisor | E23: OCONUS | H23: 26.57 | J23: =IF($I23<$H23,$H23,$I23) -> 26.57 | K23: =(J23*$K$4) -> 0 | L23: =(K23+J23)*$L$4 -> 0 | M23: =(K23+J23+L23)*$M$4 -> 0 | N23: =(J23+K23+L23+M23)*$N$4 -> 0 | O23: =SUM(J23:N23) -> 26.57 | P23: =IF($P$4<0,"N/A",$P$4*(J23+K23+L23+M23)) -> 0 | Q23: =SUM(O23:P23) -> 26.57 | R23: =O23*F23 -> 0 | S23: =P23*F23 -> 0 | T23: =Q23*F23 -> 0
B24: 019 | C24: Instructor | E24: OCONUS | H24: 26.57 | J24: =IF($I24<$H24,$H24,$I24) -> 26.57 | K24: =(J24*$K$4) -> 0 | L24: =(K24+J24)*$L$4 -> 0 | M24: =(K24+J24+L24)*$M$4 -> 0 | N24: =(J24+K24+L24+M24)*$N$4 -> 0 | O24: =SUM(J24:N24) -> 26.57 | P24: =IF($P$4<0,"N/A",$P$4*(J24+K24+L24+M24)) -> 0 | Q24: =SUM(O24:P24) -> 26.57 | R24: =O24*F24 -> 0 | S24: =P24*F24 -> 0 | T24: =Q24*F24 -> 0
A25: Total Package Fielding (TPF) and De-processing | B25: 020 | C25: Heavy Equipment Mechanic | E25: OCONUS | H25: 31.25 | J25: =IF($I25<$H25,$H25,$I25) -> 31.25 | K25: =(J25*$K$4) -> 0 | L25: =(K25+J25)*$L$4 -> 0 | M25: =(K25+J25+L25)*$M$4 -> 0 | N25: =(J25+K25+L25+M25)*$N$4 -> 0 | O25: =SUM(J25:N25) -> 31.25 | P25: =IF($P$4<0,"N/A",$P$4*(J25+K25+L25+M25)) -> 0 | Q25: =SUM(O25:P25) -> 31.25 | R25: =O25*F25 -> 0 | S25: =P25*F25 -> 0 | T25: =Q25*F25 -> 0
B26: 021 | C26: Material Handling Specialist | E26: OCONUS | H26: 27.21 | J26: =IF($I26<$H26,$H26,$I26) -> 27.21 | K26: =(J26*$K$4) -> 0 | L26: =(K26+J26)*$L$4 -> 0 | M26: =(K26+J26+L26)*$M$4 -> 0 | N26: =(J26+K26+L26+M26)*$N$4 -> 0 | O26: =SUM(J26:N26) -> 27.21 | P26: =IF($P$4<0,"N/A",$P$4*(J26+K26+L26+M26)) -> 0 | Q26: =SUM(O26:P26) -> 27.21 | R26: =O26*F26 -> 0 | S26: =P26*F26 -> 0 | T26: =Q26*F26 -> 0
B27: 022 | C27: Quality Assurance | E27: OCONUS | H27: 31.25 | J27: =IF($I27<$H27,$H27,$I27) -> 31.25 | K27: =(J27*$K$4) -> 0 | L27: =(K27+J27)*$L$4 -> 0 | M27: =(K27+J27+L27)*$M$4 -> 0 | N27: =(J27+K27+L27+M27)*$N$4 -> 0 | O27: =SUM(J27:N27) -> 31.25 | P27: =IF($P$4<0,"N/A",$P$4*(J27+K27+L27+M27)) -> 0 | Q27: =SUM(O27:P27) -> 31.25 | R27: =O27*F27 -> 0 | S27: =P27*F27 -> 0 | T27: =Q27*F27 -> 0
B28: 023 | C28: Supply/Procurement Specialist | E28: OCONUS | H28: 35.49 | J28: =IF($I28<$H28,$H28,$I28) -> 35.49 | K28: =(J28*$K$4) -> 0 | L28: =(K28+J28)*$L$4 -> 0 | M28: =(K28+J28+L28)*$M$4 -> 0 | N28: =(J28+K28+L28+M28)*$N$4 -> 0 | O28: =SUM(J28:N28) -> 35.49 | P28: =IF($P$4<0,"N/A",$P$4*(J28+K28+L28+M28)) -> 0 | Q28: =SUM(O28:P28) -> 35.49 | R28: =O28*F28 -> 0 | S28: =P28*F28 -> 0 | T28: =Q28*F28 -> 0
A29: Ordering Period 2:
A30: Ordering Period 2 Labor Categories & Hours
A31: Service | B31: ID | C31: Labor Category | D31: Reference | E31: Location | F31: Hours | H31: (Floor Rate) | I31: Direct Labor (Proposed) | J31: Direct Labor (Calculation) | K31: Fringe Benefit | L31: Labor OH 1 | M31: G&A | N31: FCCOM | O31: Cost | P31: Fee | Q31: FBLR | R31: Total Cost | S31: Total Fee | T31: Total Price
A32: CONUS
A33: Program Management | B33: 001 | C33: Project Management Specialist | D33: Section H.3.1.11 | E33: CONUS | H33: =H5+(H5*Escalation!$D$2) -> 43.81872 | I33: =I5+(I5*Escalation!$D$2) -> 0 | J33: =IF($I33<$H33,$H33,$I33) -> 43.81872 | K33: =(J33*$K$4) -> 0 | L33: =(K33+J33)*$L$4 -> 0 | M33: =(K33+J33+L33)*$M$4 -> 0 | N33: =(J33+K33+L33+M33)*$N$4 -> 0 | O33: =SUM(J33:N33) -> 43.81872 | P33: =IF($P$4<0,"N/A",$P$4*(J33+K33+L33+M33)) -> 0 | Q33: =SUM(O33:P33) -> 43.81872 | R33: =O33*F33 -> 0 | S33: =P33*F33 -> 0 | T33: =Q33*F33 -> 0
A34: Field Service Representative (FSR) | B34: 002 | C34: Field Service Representative | D34: Section H.3.1.9 | E34: CONUS | H34: =H6+(H6*Escalation!$D$2) -> 30.71232 | I34: =I6+(I6*Escalation!$D$2) -> 0 | J34: =IF($I34<$H34,$H34,$I34) -> 30.71232 | K34: =(J34*$K$4) -> 0 | L34: =(K34+J34)*$L$4 -> 0 | M34: =(K34+J34+L34)*$M$4 -> 0 | N34: =(J34+K34+L34+M34)*$N$4 -> 0 | O34: =SUM(J34:N34) -> 30.71232 | P34: =IF($P$4<0,"N/A",$P$4*(J34+K34+L34+M34)) -> 0 | Q34: =SUM(O34:P34) -> 30.71232 | R34: =O34*F34 -> 0 | S34: =P34*F34 -> 0 | T34: =Q34*F34 -> 0
A35: General Maintenance | B35: 003 | C35: Heavy Equipment Mechanic | D35: Section H.3.1.3 | E35: CONUS | H35: =H7+(H7*Escalation!$D$2) -> 30.71232 | I35: =I7+(I7*Escalation!$D$2) -> 0 | J35: =IF($I35<$H35,$H35,$I35) -> 30.71232 | K35: =(J35*$K$4) -> 0 | L35: =(K35+J35)*$L$4 -> 0 | M35: =(K35+J35+L35)*$M$4 -> 0 | N35: =(J35+K35+L35+M35)*$N$4 -> 0 | O35: =SUM(J35:N35) -> 30.71232 | P35: =IF($P$4<0,"N/A",$P$4*(J35+K35+L35+M35)) -> 0 | Q35: =SUM(O35:P35) -> 30.71232 | R35: =O35*F35 -> 0 | S35: =P35*F35 -> 0 | T35: =Q35*F35 -> 0
A36: Modified Work Orders (MWO) | B36: 004 | C36: Field Service Representative | D36: Section H.3.1.9 | E36: CONUS | H36: =H8+(H8*Escalation!$D$2) -> 30.71232 | I36: =I8+(I8*Escalation!$D$2) -> 0 | J36: =IF($I36<$H36,$H36,$I36) -> 30.71232 | K36: =(J36*$K$4) -> 0 | L36: =(K36+J36)*$L$4 -> 0 | M36: =(K36+J36+L36)*$M$4 -> 0 | N36: =(J36+K36+L36+M36)*$N$4 -> 0 | O36: =SUM(J36:N36) -> 30.71232 | P36: =IF($P$4<0,"N/A",$P$4*(J36+K36+L36+M36)) -> 0 | Q36: =SUM(O36:P36) -> 30.71232 | R36: =O36*F36 -> 0 | S36: =P36*F36 -> 0 | T36: =Q36*F36 -> 0
B37: 005 | C37: Modified Work Orders (MWO) | D37: Section H.3.1.6 | E37: CONUS | H37: =H9+(H9*Escalation!$D$2) -> 30.71232 | I37: =I9+(I9*Escalation!$D$2) -> 0 | J37: =IF($I37<$H37,$H37,$I37) -> 30.71232 | K37: =(J37*$K$4) -> 0 | L37: =(K37+J37)*$L$4 -> 0 | M37: =(K37+J37+L37)*$M$4 -> 0 | N37: =(J37+K37+L37+M37)*$N$4 -> 0 | O37: =SUM(J37:N37) -> 30.71232 | P37: =IF($P$4<0,"N/A",$P$4*(J37+K37+L37+M37)) -> 0 | Q37: =SUM(O37:P37) -> 30.71232 | R37: =O37*F37 -> 0 | S37: =P37*F37 -> 0 | T37: =Q37*F37 -> 0
B38: 006 | C38: Quality Assurance | D38: Section H.3.1.10 | E38: CONUS | H38: =H10+(H10*Escalation!$D$2) -> 30.71232 | I38: =I10+(I10*Escalation!$D$2) -> 0 | J38: =IF($I38<$H38,$H38,$I38) -> 30.71232 | K38: =(J38*$K$4) -> 0 | L38: =(K38+J38)*$L$4 -> 0 | M38: =(K38+J38+L38)*$M$4 -> 0 | N38: =(J38+K38+L38+M38)*$N$4 -> 0 | O38: =SUM(J38:N38) -> 30.71232 | P38: =IF($P$4<0,"N/A",$P$4*(J38+K38+L38+M38)) -> 0 | Q38: =SUM(O38:P38) -> 30.71232 | R38: =O38*F38 -> 0 | S38: =P38*F38 -> 0 | T38: =Q38*F38 -> 0
B39: 007 | C39: Software | D39: Section H.3.1.5 | E39: CONUS | H39: =H11+(H11*Escalation!$D$2) -> 30.71232 | I39: =I11+(I11*Escalation!$D$2) -> 0 | J39: =IF($I39<$H39,$H39,$I39) -> 30.71232 | K39: =(J39*$K$4) -> 0 | L39: =(K39+J39)*$L$4 -> 0 | M39: =(K39+J39+L39)*$M$4 -> 0 | N39: =(J39+K39+L39+M39)*$N$4 -> 0 | O39: =SUM(J39:N39) -> 30.71232 | P39: =IF($P$4<0,"N/A",$P$4*(J39+K39+L39+M39)) -> 0 | Q39: =SUM(O39:P39) -> 30.71232 | R39: =O39*F39 -> 0 | S39: =P39*F39 -> 0 | T39: =Q39*F39 -> 0
B40: 008 | C40: Welder | D40: Section H.3.1.4 | E40: CONUS | H40: =H12+(H12*Escalation!$D$2) -> 24.32424 | I40: =I12+(I12*Escalation!$D$2) -> 0 | J40: =IF($I40<$H40,$H40,$I40) -> 24.32424 | K40: =(J40*$K$4) -> 0 | L40: =(K40+J40)*$L$4 -> 0 | M40: =(K40+J40+L40)*$M$4 -> 0 | N40: =(J40+K40+L40+M40)*$N$4 -> 0 | O40: =SUM(J40:N40) -> 24.32424 | P40: =IF($P$4<0,"N/A",$P$4*(J40+K40+L40+M40)) -> 0 | Q40: =SUM(O40:P40) -> 24.32424 | R40: =O40*F40 -> 0 | S40: =P40*F40 -> 0 | T40: =Q40*F40 -> 0
A41: New Equipment Training (NET) | B41: 009 | C41: Instructor Supervisor | D41: Section H.3.1.7 | E41: CONUS | H41: =H13+(H13*Escalation!$D$2) -> 26.1096 | I41: =I13+(I13*Escalation!$D$2) -> 0 | J41: =IF($I41<$H41,$H41,$I41) -> 26.1096 | K41: =(J41*$K$4) -> 0 | L41: =(K41+J41)*$L$4 -> 0 | M41: =(K41+J41+L41)*$M$4 -> 0 | N41: =(J41+K41+L41+M41)*$N$4 -> 0 | O41: =SUM(J41:N41) -> 26.1096 | P41: =IF($P$4<0,"N/A",$P$4*(J41+K41+L41+M41)) -> 0 | Q41: =SUM(O41:P41) -> 26.1096 | R41: =O41*F41 -> 0 | S41: =P41*F41 -> 0 | T41: =Q41*F41 -> 0
B42: 010 | C42: Instructor | D42: Section H.3.1.8 | E42: CONUS | H42: =H14+(H14*Escalation!$D$2) -> 26.1096 | I42: =I14+(I14*Escalation!$D$2) -> 0 | J42: =IF($I42<$H42,$H42,$I42) -> 26.1096 | K42: =(J42*$K$4) -> 0 | L42: =(K42+J42)*$L$4 -> 0 | M42: =(K42+J42+L42)*$M$4 -> 0 | N42: =(J42+K42+L42+M42)*$N$4 -> 0 | O42: =SUM(J42:N42) -> 26.1096 | P42: =IF($P$4<0,"N/A",$P$4*(J42+K42+L42+M42)) -> 0 | Q42: =SUM(O42:P42) -> 26.1096 | R42: =O42*F42 -> 0 | S42: =P42*F42 -> 0 | T42: =Q42*F42 -> 0
A43: Total Package Fielding (TPF) and De-processing | B43: 011 | C43: Heavy Equipment Mechanic | D43: Section H.3.1.3 | E43: CONUS | H43: =H15+(H15*Escalation!$D$2) -> 30.71232 | I43: =I15+(I15*Escalation!$D$2) -> 0 | J43: =IF($I43<$H43,$H43,$I43) -> 30.71232 | K43: =(J43*$K$4) -> 0 | L43: =(K43+J43)*$L$4 -> 0 | M43: =(K43+J43+L43)*$M$4 -> 0 | N43: =(J43+K43+L43+M43)*$N$4 -> 0 | O43: =SUM(J43:N43) -> 30.71232 | P43: =IF($P$4<0,"N/A",$P$4*(J43+K43+L43+M43)) -> 0 | Q43: =SUM(O43:P43) -> 30.71232 | R43: =O43*F43 -> 0 | S43: =P43*F43 -> 0 | T43: =Q43*F43 -> 0
B44: 012 | C44: Material Handling Specialist | D44: Section H.3.1.2 | E44: CONUS | H44: =H16+(H16*Escalation!$D$2) -> 26.73912 | I44: =I16+(I16*Escalation!$D$2) -> 0 | J44: =IF($I44<$H44,$H44,$I44) -> 26.73912 | K44: =(J44*$K$4) -> 0 | L44: =(K44+J44)*$L$4 -> 0 | M44: =(K44+J44+L44)*$M$4 -> 0 | N44: =(J44+K44+L44+M44)*$N$4 -> 0 | O44: =SUM(J44:N44) -> 26.73912 | P44: =IF($P$4<0,"N/A",$P$4*(J44+K44+L44+M44)) -> 0 | Q44: =SUM(O44:P44) -> 26.73912 | R44: =O44*F44 -> 0 | S44: =P44*F44 -> 0 | T44: =Q44*F44 -> 0
B45: 013 | C45: Quality Assurance | D45: Section H.3.1.10 | E45: CONUS | H45: =H17+(H17*Escalation!$D$2) -> 30.71232 | I45: =I17+(I17*Escalation!$D$2) -> 0 | J45: =IF($I45<$H45,$H45,$I45) -> 30.71232 | K45: =(J45*$K$4) -> 0 | L45: =(K45+J45)*$L$4 -> 0 | M45: =(K45+J45+L45)*$M$4 -> 0 | N45: =(J45+K45+L45+M45)*$N$4 -> 0 | O45: =SUM(J45:N45) -> 30.71232 | P45: =IF($P$4<0,"N/A",$P$4*(J45+K45+L45+M45)) -> 0 | Q45: =SUM(O45:P45) -> 30.71232 | R45: =O45*F45 -> 0 | S45: =P45*F45 -> 0 | T45: =Q45*F45 -> 0
B46: 014 | C46: Supply/Procurement Specialist | D46: Section H.3.1.1 | E46: CONUS | H46: =H18+(H18*Escalation!$D$2) -> 34.8816 | I46: =I18+(I18*Escalation!$D$2) -> 0 | J46: =IF($I46<$H46,$H46,$I46) -> 34.8816 | K46: =(J46*$K$4) -> 0 | L46: =(K46+J46)*$L$4 -> 0 | M46: =(K46+J46+L46)*$M$4 -> 0 | N46: =(J46+K46+L46+M46)*$N$4 -> 0 | O46: =SUM(J46:N46) -> 34.8816 | P46: =IF($P$4<0,"N/A",$P$4*(J46+K46+L46+M46)) -> 0 | Q46: =SUM(O46:P46) -> 34.8816 | R46: =O46*F46 -> 0 | S46: =P46*F46 -> 0 | T46: =Q46*F46 -> 0
B47: 015 | C47: Welder | D47: Section H.3.1.4 | E47: CONUS | H47: =H19+(H19*Escalation!$D$2) -> 24.32424 | I47: =I19+(I19*Escalation!$D$2) -> 0 | J47: =IF($I47<$H47,$H47,$I47) -> 24.32424 | K47: =(J47*$K$4) -> 0 | L47: =(K47+J47)*$L$4 -> 0 | M47: =(K47+J47+L47)*$M$4 -> 0 | N47: =(J47+K47+L47+M47)*$N$4 -> 0 | O47: =SUM(J47:N47) -> 24.32424 | P47: =IF($P$4<0,"N/A",$P$4*(J47+K47+L47+M47)) -> 0 | Q47: =SUM(O47:P47) -> 24.32424 | R47: =O47*F47 -> 0 | S47: =P47*F47 -> 0 | T47: =Q47*F47 -> 0
A48: OCONUS
A49: Field Service Representative (FSR) | B49: 016 | C49: Field Service Representative | E49: OCONUS | H49: =H21+(H21*Escalation!$D$2) -> 32.25 | I49: =I21+(I21*Escalation!$D$2) -> 0 | J49: =IF($I49<$H49,$H49,$I49) -> 32.25 | K49: =(J49*$K$4) -> 0 | L49: =(K49+J49)*$L$4 -> 0 | M49: =(K49+J49+L49)*$M$4 -> 0 | N49: =(J49+K49+L49+M49)*$N$4 -> 0 | O49: =SUM(J49:N49) -> 32.25 | P49: =IF($P$4<0,"N/A",$P$4*(J49+K49+L49+M49)) -> 0 | Q49: =SUM(O49:P49) -> 32.25 | R49: =O49*F49 -> 0 | S49: =P49*F49 -> 0 | T49: =Q49*F49 -> 0
A50: General Maintenance | B50: 017 | C50: Heavy Equipment Mechanic | E50: OCONUS | H50: =H22+(H22*Escalation!$D$2) -> 32.25 | I50: =I22+(I22*Escalation!$D$2) -> 0 | J50: =IF($I50<$H50,$H50,$I50) -> 32.25 | K50: =(J50*$K$4) -> 0 | L50: =(K50+J50)*$L$4 -> 0 | M50: =(K50+J50+L50)*$M$4 -> 0 | N50: =(J50+K50+L50+M50)*$N$4 -> 0 | O50: =SUM(J50:N50) -> 32.25 | P50: =IF($P$4<0,"N/A",$P$4*(J50+K50+L50+M50)) -> 0 | Q50: =SUM(O50:P50) -> 32.25 | R50: =O50*F50 -> 0 | S50: =P50*F50 -> 0 | T50: =Q50*F50 -> 0
A51: New Equipment Training (NET) | B51: 018 | C51: Instructor Supervisor | E51: OCONUS | H51: =H23+(H23*Escalation!$D$2) -> 27.42024 | I51: =I23+(I23*Escalation!$D$2) -> 0 | J51: =IF($I51<$H51,$H51,$I51) -> 27.42024 | K51: =(J51*$K$4) -> 0 | L51: =(K51+J51)*$L$4 -> 0 | M51: =(K51+J51+L51)*$M$4 -> 0 | N51: =(J51+K51+L51+M51)*$N$4 -> 0 | O51: =SUM(J51:N51) -> 27.42024 | P51: =IF($P$4<0,"N/A",$P$4*(J51+K51+L51+M51)) -> 0 | Q51: =SUM(O51:P51) -> 27.42024 | R51: =O51*F51 -> 0 | S51: =P51*F51 -> 0 | T51: =Q51*F51 -> 0
B52: 019 | C52: Instructor | E52: OCONUS | H52: =H24+(H24*Escalation!$D$2) -> 27.42024 | I52: =I24+(I24*Escalation!$D$2) -> 0 | J52: =IF($I52<$H52,$H52,$I52) -> 27.42024 | K52: =(J52*$K$4) -> 0 | L52: =(K52+J52)*$L$4 -> 0 | M52: =(K52+J52+L52)*$M$4 -> 0 | N52: =(J52+K52+L52+M52)*$N$4 -> 0 | O52: =SUM(J52:N52) -> 27.42024 | P52: =IF($P$4<0,"N/A",$P$4*(J52+K52+L52+M52)) -> 0 | Q52: =SUM(O52:P52) -> 27.42024 | R52: =O52*F52 -> 0 | S52: =P52*F52 -> 0 | T52: =Q52*F52 -> 0
A53: Total Package Fielding (TPF) and De-processing | B53: 020 | C53: Heavy Equipment Mechanic | E53: OCONUS | H53: =H25+(H25*Escalation!$D$2) -> 32.25 | I53: =I25+(I25*Escalation!$D$2) -> 0 | J53: =IF($I53<$H53,$H53,$I53) -> 32.25 | K53: =(J53*$K$4) -> 0 | L53: =(K53+J53)*$L$4 -> 0 | M53: =(K53+J53+L53)*$M$4 -> 0 | N53: =(J53+K53+L53+M53)*$N$4 -> 0 | O53: =SUM(J53:N53) -> 32.25 | P53: =IF($P$4<0,"N/A",$P$4*(J53+K53+L53+M53)) -> 0 | Q53: =SUM(O53:P53) -> 32.25 | R53: =O53*F53 -> 0 | S53: =P53*F53 -> 0 | T53: =Q53*F53 -> 0
B54: 021 | C54: Material Handling Specialist | E54: OCONUS | H54: =H26+(H26*Escalation!$D$2) -> 28.08072 | I54: =I26+(I26*Escalation!$D$2) -> 0 | J54: =IF($I54<$H54,$H54,$I54) -> 28.08072 | K54: =(J54*$K$4) -> 0 | L54: =(K54+J54)*$L$4 -> 0 | M54: =(K54+J54+L54)*$M$4 -> 0 | N54: =(J54+K54+L54+M54)*$N$4 -> 0 | O54: =SUM(J54:N54) -> 28.08072 | P54: =IF($P$4<0,"N/A",$P$4*(J54+K54+L54+M54)) -> 0 | Q54: =SUM(O54:P54) -> 28.08072 | R54: =O54*F54 -> 0 | S54: =P54*F54 -> 0 | T54: =Q54*F54 -> 0
B55: 022 | C55: Quality Assurance | E55: OCONUS | H55: =H27+(H27*Escalation!$D$2) -> 32.25 | I55: =I27+(I27*Escalation!$D$2) -> 0 | J55: =IF($I55<$H55,$H55,$I55) -> 32.25 | K55: =(J55*$K$4) -> 0 | L55: =(K55+J55)*$L$4 -> 0 | M55: =(K55+J55+L55)*$M$4 -> 0 | N55: =(J55+K55+L55+M55)*$N$4 -> 0 | O55: =SUM(J55:N55) -> 32.25 | P55: =IF($P$4<0,"N/A",$P$4*(J55+K55+L55+M55)) -> 0 | Q55: =SUM(O55:P55) -> 32.25 | R55: =O55*F55 -> 0 | S55: =P55*F55 -> 0 | T55: =Q55*F55 -> 0
B56: 023 | C56: Supply/Procurement Specialist | E56: OCONUS | H56: =H28+(H28*Escalation!$D$2) -> 36.62568 | I56: =I28+(I28*Escalation!$D$2) -> 0 | J56: =IF($I56<$H56,$H56,$I56) -> 36.62568 | K56: =(J56*$K$4) -> 0 | L56: =(K56+J56)*$L$4 -> 0 | M56: =(K56+J56+L56)*$M$4 -> 0 | N56: =(J56+K56+L56+M56)*$N$4 -> 0 | O56: =SUM(J56:N56) -> 36.62568 | P56: =IF($P$4<0,"N/A",$P$4*(J56+K56+L56+M56)) -> 0 | Q56: =SUM(O56:P56) -> 36.62568 | R56: =O56*F56 -> 0 | S56: =P56*F56 -> 0 | T56: =Q56*F56 -> 0
A57: Ordering Period 3:
A58: Ordering Period 3 Labor Categories & Hours
A59: Service | B59: ID | C59: Labor Category | D59: Reference | E59: Location | F59: Hours | H59: (Floor Rate) | I59: Direct Labor (Proposed) | J59: Direct Labor (Calculation) | K59: Fringe Benefit | L59: Labor OH 1 | M59: G&A | N59: FCCOM | O59: Cost | P59: Fee | Q59: FBLR | R59: Total Cost | S59: Total Fee | T59: Total Price
A60: CONUS
A61: Program Management | B61: 001 | C61: Project Management Specialist | D61: Section H.3.1.11 | E61: CONUS | H61: =H33+(H33*Escalation!$D$3) -> 45.001825 | I61: =I33+(I33*Escalation!$D$3) -> 0 | J61: =IF($I61<$H61,$H61,$I61) -> 45.001825 | K61: =(J61*$K$4) -> 0 | L61: =(K61+J61)*$L$4 -> 0 | M61: =(K61+J61+L61)*$M$4 -> 0 | N61: =(J61+K61+L61+M61)*$N$4 -> 0 | O61: =SUM(J61:N61) -> 45.001825 | P61: =IF($P$4<0,"N/A",$P$4*(J61+K61+L61+M61)) -> 0 | Q61: =SUM(O61:P61) -> 45.001825 | R61: =O61*F61 -> 0 | S61: =P61*F61 -> 0 | T61: =Q61*F61 -> 0
A62: Field Service Representative (FSR) | B62: 002 | C62: Field Service Representative | D62: Section H.3.1.9 | E62: CONUS | H62: =H34+(H34*Escalation!$D$3) -> 31.541553 | I62: =I34+(I34*Escalation!$D$3) -> 0 | J62: =IF($I62<$H62,$H62,$I62) -> 31.541553 | K62: =(J62*$K$4) -> 0 | L62: =(K62+J62)*$L$4 -> 0 | M62: =(K62+J62+L62)*$M$4 -> 0 | N62: =(J62+K62+L62+M62)*$N$4 -> 0 | O62: =SUM(J62:N62) -> 31.541553 | P62: =IF($P$4<0,"N/A",$P$4*(J62+K62+L62+M62)) -> 0 | Q62: =SUM(O62:P62) -> 31.541553 | R62: =O62*F62 -> 0 | S62: =P62*F62 -> 0 | T62: =Q62*F62 -> 0
A63: General Maintenance | B63: 003 | C63: Heavy Equipment Mechanic | D63: Section H.3.1.3 | E63: CONUS | H63: =H35+(H35*Escalation!$D$3) -> 31.541553 | I63: =I35+(I35*Escalation!$D$3) -> 0 | J63: =IF($I63<$H63,$H63,$I63) -> 31.541553 | K63: =(J63*$K$4) -> 0 | L63: =(K63+J63)*$L$4 -> 0 | M63: =(K63+J63+L63)*$M$4 -> 0 | N63: =(J63+K63+L63+M63)*$N$4 -> 0 | O63: =SUM(J63:N63) -> 31.541553 | P63: =IF($P$4<0,"N/A",$P$4*(J63+K63+L63+M63)) -> 0 | Q63: =SUM(O63:P63) -> 31.541553 | R63: =O63*F63 -> 0 | S63: =P63*F63 -> 0 | T63: =Q63*F63 -> 0
A64: Modified Work Orders (MWO) | B64: 004 | C64: Field Service Representative | D64: Section H.3.1.9 | E64: CONUS | H64: =H36+(H36*Escalation!$D$3) -> 31.541553 | I64: =I36+(I36*Escalation!$D$3) -> 0 | J64: =IF($I64<$H64,$H64,$I64) -> 31.541553 | K64: =(J64*$K$4) -> 0 | L64: =(K64+J64)*$L$4 -> 0 | M64: =(K64+J64+L64)*$M$4 -> 0 | N64: =(J64+K64+L64+M64)*$N$4 -> 0 | O64: =SUM(J64:N64) -> 31.541553 | P64: =IF($P$4<0,"N/A",$P$4*(J64+K64+L64+M64)) -> 0 | Q64: =SUM(O64:P64) -> 31.541553 | R64: =O64*F64 -> 0 | S64: =P64*F64 -> 0 | T64: =Q64*F64 -> 0
B65: 005 | C65: Modified Work Orders (MWO) | D65: Section H.3.1.6 | E65: CONUS | H65: =H37+(H37*Escalation!$D$3) -> 31.541553 | I65: =I37+(I37*Escalation!$D$3) -> 0 | J65: =IF($I65<$H65,$H65,$I65) -> 31.541553 | K65: =(J65*$K$4) -> 0 | L65: =(K65+J65)*$L$4 -> 0 | M65: =(K65+J65+L65)*$M$4 -> 0 | N65: =(J65+K65+L65+M65)*$N$4 -> 0 | O65: =SUM(J65:N65) -> 31.541553 | P65: =IF($P$4<0,"N/A",$P$4*(J65+K65+L65+M65)) -> 0 | Q65: =SUM(O65:P65) -> 31.541553 | R65: =O65*F65 -> 0 | S65: =P65*F65 -> 0 | T65: =Q65*F65 -> 0
B66: 006 | C66: Quality Assurance | D66: Section H.3.1.10 | E66: CONUS | H66: =H38+(H38*Escalation!$D$3) -> 31.541553 | I66: =I38+(I38*Escalation!$D$3) -> 0 | J66: =IF($I66<$H66,$H66,$I66) -> 31.541553 | K66: =(J66*$K$4) -> 0 | L66: =(K66+J66)*$L$4 -> 0 | M66: =(K66+J66+L66)*$M$4 -> 0 | N66: =(J66+K66+L66+M66)*$N$4 -> 0 | O66: =SUM(J66:N66) -> 31.541553 | P66: =IF($P$4<0,"N/A",$P$4*(J66+K66+L66+M66)) -> 0 | Q66: =SUM(O66:P66) -> 31.541553 | R66: =O66*F66 -> 0 | S66: =P66*F66 -> 0 | T66: =Q66*F66 -> 0
B67: 007 | C67: Software | D67: Section H.3.1.5 | E67: CONUS | H67: =H39+(H39*Escalation!$D$3) -> 31.541553 | I67: =I39+(I39*Escalation!$D$3) -> 0 | J67: =IF($I67<$H67,$H67,$I67) -> 31.541553 | K67: =(J67*$K$4) -> 0 | L67: =(K67+J67)*$L$4 -> 0 | M67: =(K67+J67+L67)*$M$4 -> 0 | N67: =(J67+K67+L67+M67)*$N$4 -> 0 | O67: =SUM(J67:N67) -> 31.541553 | P67: =IF($P$4<0,"N/A",$P$4*(J67+K67+L67+M67)) -> 0 | Q67: =SUM(O67:P67) -> 31.541553 | R67: =O67*F67 -> 0 | S67: =P67*F67 -> 0 | T67: =Q67*F67 -> 0
B68: 008 | C68: Welder | D68: Section H.3.1.4 | E68: CONUS | H68: =H40+(H40*Escalation!$D$3) -> 24.980994 | I68: =I40+(I40*Escalation!$D$3) -> 0 | J68: =IF($I68<$H68,$H68,$I68) -> 24.980994 | K68: =(J68*$K$4) -> 0 | L68: =(K68+J68)*$L$4 -> 0 | M68: =(K68+J68+L68)*$M$4 -> 0 | N68: =(J68+K68+L68+M68)*$N$4 -> 0 | O68: =SUM(J68:N68) -> 24.980994 | P68: =IF($P$4<0,"N/A",$P$4*(J68+K68+L68+M68)) -> 0 | Q68: =SUM(O68:P68) -> 24.980994 | R68: =O68*F68 -> 0 | S68: =P68*F68 -> 0 | T68: =Q68*F68 -> 0
A69: New Equipment Training (NET) | B69: 009 | C69: Instructor Supervisor | D69: Section H.3.1.7 | E69: CONUS | H69: =H41+(H41*Escalation!$D$3) -> 26.814559 | I69: =I41+(I41*Escalation!$D$3) -> 0 | J69: =IF($I69<$H69,$H69,$I69) -> 26.814559 | K69: =(J69*$K$4) -> 0 | L69: =(K69+J69)*$L$4 -> 0 | M69: =(K69+J69+L69)*$M$4 -> 0 | N69: =(J69+K69+L69+M69)*$N$4 -> 0 | O69: =SUM(J69:N69) -> 26.814559 | P69: =IF($P$4<0,"N/A",$P$4*(J69+K69+L69+M69)) -> 0 | Q69: =SUM(O69:P69) -> 26.814559 | R69: =O69*F69 -> 0 | S69: =P69*F69 -> 0 | T69: =Q69*F69 -> 0
B70: 010 | C70: Instructor | D70: Section H.3.1.8 | E70: CONUS | H70: =H42+(H42*Escalation!$D$3) -> 26.814559 | I70: =I42+(I42*Escalation!$D$3) -> 0 | J70: =IF($I70<$H70,$H70,$I70) -> 26.814559 | K70: =(J70*$K$4) -> 0 | L70: =(K70+J70)*$L$4 -> 0 | M70: =(K70+J70+L70)*$M$4 -> 0 | N70: =(J70+K70+L70+M70)*$N$4 -> 0 | O70: =SUM(J70:N70) -> 26.814559 | P70: =IF($P$4<0,"N/A",$P$4*(J70+K70+L70+M70)) -> 0 | Q70: =SUM(O70:P70) -> 26.814559 | R70: =O70*F70 -> 0 | S70: =P70*F70 -> 0 | T70: =Q70*F70 -> 0
A71: Total Package Fielding (TPF) and De-processing | B71: 011 | C71: Heavy Equipment Mechanic | D71: Section H.3.1.3 | E71: CONUS | H71: =H43+(H43*Escalation!$D$3) -> 31.541553 | I71: =I43+(I43*Escalation!$D$3) -> 0 | J71: =IF($I71<$H71,$H71,$I71) -> 31.541553 | K71: =(J71*$K$4) -> 0 | L71: =(K71+J71)*$L$4 -> 0 | M71: =(K71+J71+L71)*$M$4 -> 0 | N71: =(J71+K71+L71+M71)*$N$4 -> 0 | O71: =SUM(J71:N71) -> 31.541553 | P71: =IF($P$4<0,"N/A",$P$4*(J71+K71+L71+M71)) -> 0 | Q71: =SUM(O71:P71) -> 31.541553 | R71: =O71*F71 -> 0 | S71: =P71*F71 -> 0 | T71: =Q71*F71 -> 0
B72: 012 | C72: Material Handling Specialist | D72: Section H.3.1.2 | E72: CONUS | H72: =H44+(H44*Escalation!$D$3) -> 27.461076 | I72: =I44+(I44*Escalation!$D$3) -> 0 | J72: =IF($I72<$H72,$H72,$I72) -> 27.461076 | K72: =(J72*$K$4) -> 0 | L72: =(K72+J72)*$L$4 -> 0 | M72: =(K72+J72+L72)*$M$4 -> 0 | N72: =(J72+K72+L72+M72)*$N$4 -> 0 | O72: =SUM(J72:N72) -> 27.461076 | P72: =IF($P$4<0,"N/A",$P$4*(J72+K72+L72+M72)) -> 0 | Q72: =SUM(O72:P72) -> 27.461076 | R72: =O72*F72 -> 0 | S72: =P72*F72 -> 0 | T72: =Q72*F72 -> 0
B73: 013 | C73: Quality Assurance | D73: Section H.3.1.10 | E73: CONUS | H73: =H45+(H45*Escalation!$D$3) -> 31.541553 | I73: =I45+(I45*Escalation!$D$3) -> 0 | J73: =IF($I73<$H73,$H73,$I73) -> 31.541553 | K73: =(J73*$K$4) -> 0 | L73: =(K73+J73)*$L$4 -> 0 | M73: =(K73+J73+L73)*$M$4 -> 0 | N73: =(J73+K73+L73+M73)*$N$4 -> 0 | O73: =SUM(J73:N73) -> 31.541553 | P73: =IF($P$4<0,"N/A",$P$4*(J73+K73+L73+M73)) -> 0 | Q73: =SUM(O73:P73) -> 31.541553 | R73: =O73*F73 -> 0 | S73: =P73*F73 -> 0 | T73: =Q73*F73 -> 0
B74: 014 | C74: Supply/Procurement Specialist | D74: Section H.3.1.1 | E74: CONUS | H74: =H46+(H46*Escalation!$D$3) -> 35.823403 | I74: =I46+(I46*Escalation!$D$3) -> 0 | J74: =IF($I74<$H74,$H74,$I74) -> 35.823403 | K74: =(J74*$K$4) -> 0 | L74: =(K74+J74)*$L$4 -> 0 | M74: =(K74+J74+L74)*$M$4 -> 0 | N74: =(J74+K74+L74+M74)*$N$4 -> 0 | O74: =SUM(J74:N74) -> 35.823403 | P74: =IF($P$4<0,"N/A",$P$4*(J74+K74+L74+M74)) -> 0 | Q74: =SUM(O74:P74) -> 35.823403 | R74: =O74*F74 -> 0 | S74: =P74*F74 -> 0 | T74: =Q74*F74 -> 0
B75: 015 | C75: Welder | D75: Section H.3.1.4 | E75: CONUS | H75: =H47+(H47*Escalation!$D$3) -> 24.980994 | I75: =I47+(I47*Escalation!$D$3) -> 0 | J75: =IF($I75<$H75,$H75,$I75) -> 24.980994 | K75: =(J75*$K$4) -> 0 | L75: =(K75+J75)*$L$4 -> 0 | M75: =(K75+J75+L75)*$M$4 -> 0 | N75: =(J75+K75+L75+M75)*$N$4 -> 0 | O75: =SUM(J75:N75) -> 24.980994 | P75: =IF($P$4<0,"N/A",$P$4*(J75+K75+L75+M75)) -> 0 | Q75: =SUM(O75:P75) -> 24.980994 | R75: =O75*F75 -> 0 | S75: =P75*F75 -> 0 | T75: =Q75*F75 -> 0
A76: OCONUS
A77: Field Service Representative (FSR) | B77: 016 | C77: Field Service Representative | E77: OCONUS | H77: =H49+(H49*Escalation!$D$3) -> 33.12075 | I77: =I49+(I49*Escalation!$D$3) -> 0 | J77: =IF($I77<$H77,$H77,$I77) -> 33.12075 | K77: =(J77*$K$4) -> 0 | L77: =(K77+J77)*$L$4 -> 0 | M77: =(K77+J77+L77)*$M$4 -> 0 | N77: =(J77+K77+L77+M77)*$N$4 -> 0 | O77: =SUM(J77:N77) -> 33.12075 | P77: =IF($P$4<0,"N/A",$P$4*(J77+K77+L77+M77)) -> 0 | Q77: =SUM(O77:P77) -> 33.12075 | R77: =O77*F77 -> 0 | S77: =P77*F77 -> 0 | T77: =Q77*F77 -> 0
A78: General Maintenance | B78: 017 | C78: Heavy Equipment Mechanic | E78: OCONUS | H78: =H50+(H50*Escalation!$D$3) -> 33.12075 | I78: =I50+(I50*Escalation!$D$3) -> 0 | J78: =IF($I78<$H78,$H78,$I78) -> 33.12075 | K78: =(J78*$K$4) -> 0 | L78: =(K78+J78)*$L$4 -> 0 | M78: =(K78+J78+L78)*$M$4 -> 0 | N78: =(J78+K78+L78+M78)*$N$4 -> 0 | O78: =SUM(J78:N78) -> 33.12075 | P78: =IF($P$4<0,"N/A",$P$4*(J78+K78+L78+M78)) -> 0 | Q78: =SUM(O78:P78) -> 33.12075 | R78: =O78*F78 -> 0 | S78: =P78*F78 -> 0 | T78: =Q78*F78 -> 0
A79: New Equipment Training (NET) | B79: 018 | C79: Instructor Supervisor | E79: OCONUS | H79: =H51+(H51*Escalation!$D$3) -> 28.160586 | I79: =I51+(I51*Escalation!$D$3) -> 0 | J79: =IF($I79<$H79,$H79,$I79) -> 28.160586 | K79: =(J79*$K$4) -> 0 | L79: =(K79+J79)*$L$4 -> 0 | M79: =(K79+J79+L79)*$M$4 -> 0 | N79: =(J79+K79+L79+M79)*$N$4 -> 0 | O79: =SUM(J79:N79) -> 28.160586 | P79: =IF($P$4<0,"N/A",$P$4*(J79+K79+L79+M79)) -> 0 | Q79: =SUM(O79:P79) -> 28.160586 | R79: =O79*F79 -> 0 | S79: =P79*F79 -> 0 | T79: =Q79*F79 -> 0
B80: 019 | C80: Instructor | E80: OCONUS | H80: =H52+(H52*Escalation!$D$3) -> 28.160586 | I80: =I52+(I52*Escalation!$D$3) -> 0 | J80: =IF($I80<$H80,$H80,$I80) -> 28.160586 | K80: =(J80*$K$4) -> 0 | L80: =(K80+J80)*$L$4 -> 0 | M80: =(K80+J80+L80)*$M$4 -> 0 | N80: =(J80+K80+L80+M80)*$N$4 -> 0 | O80: =SUM(J80:N80) -> 28.160586 | P80: =IF($P$4<0,"N/A",$P$4*(J80+K80+L80+M80)) -> 0 | Q80: =SUM(O80:P80) -> 28.160586 | R80: =O80*F80 -> 0 | S80: =P80*F80 -> 0 | T80: =Q80*F80 -> 0
A81: Total Package Fielding (TPF) and De-processing | B81: 020 | C81: Heavy Equipment Mechanic | E81: OCONUS | H81: =H53+(H53*Escalation!$D$3) -> 33.12075 | I81: =I53+(I53*Escalation!$D$3) -> 0 | J81: =IF($I81<$H81,$H81,$I81) -> 33.12075 | K81: =(J81*$K$4) -> 0 | L81: =(K81+J81)*$L$4 -> 0 | M81: =(K81+J81+L81)*$M$4 -> 0 | N81: =(J81+K81+L81+M81)*$N$4 -> 0 | O81: =SUM(J81:N81) -> 33.12075 | P81: =IF($P$4<0,"N/A",$P$4*(J81+K81+L81+M81)) -> 0 | Q81: =SUM(O81:P81) -> 33.12075 | R81: =O81*F81 -> 0 | S81: =P81*F81 -> 0 | T81: =Q81*F81 -> 0
B82: 021 | C82: Material Handling Specialist | E82: OCONUS | H82: =H54+(H54*Escalation!$D$3) -> 28.838899 | I82: =I54+(I54*Escalation!$D$3) -> 0 | J82: =IF($I82<$H82,$H82,$I82) -> 28.838899 | K82: =(J82*$K$4) -> 0 | L82: =(K82+J82)*$L$4 -> 0 | M82: =(K82+J82+L82)*$M$4 -> 0 | N82: =(J82+K82+L82+M82)*$N$4 -> 0 | O82: =SUM(J82:N82) -> 28.838899 | P82: =IF($P$4<0,"N/A",$P$4*(J82+K82+L82+M82)) -> 0 | Q82: =SUM(O82:P82) -> 28.838899 | R82: =O82*F82 -> 0 | S82: =P82*F82 -> 0 | T82: =Q82*F82 -> 0
B83: 022 | C83: Quality Assurance | E83: OCONUS | H83: =H55+(H55*Escalation!$D$3) -> 33.12075 | I83: =I55+(I55*Escalation!$D$3) -> 0 | J83: =IF($I83<$H83,$H83,$I83) -> 33.12075 | K83: =(J83*$K$4) -> 0 | L83: =(K83+J83)*$L$4 -> 0 | M83: =(K83+J83+L83)*$M$4 -> 0 | N83: =(J83+K83+L83+M83)*$N$4 -> 0 | O83: =SUM(J83:N83) -> 33.12075 | P83: =IF($P$4<0,"N/A",$P$4*(J83+K83+L83+M83)) -> 0 | Q83: =SUM(O83:P83) -> 33.12075 | R83: =O83*F83 -> 0 | S83: =P83*F83 -> 0 | T83: =Q83*F83 -> 0
B84: 023 | C84: Supply/Procurement Specialist | E84: OCONUS | H84: =H56+(H56*Escalation!$D$3) -> 37.614573 | I84: =I56+(I56*Escalation!$D$3) -> 0 | J84: =IF($I84<$H84,$H84,$I84) -> 37.614573 | K84: =(J84*$K$4) -> 0 | L84: =(K84+J84)*$L$4 -> 0 | M84: =(K84+J84+L84)*$M$4 -> 0 | N84: =(J84+K84+L84+M84)*$N$4 -> 0 | O84: =SUM(J84:N84) -> 37.614573 | P84: =IF($P$4<0,"N/A",$P$4*(J84+K84+L84+M84)) -> 0 | Q84: =SUM(O84:P84) -> 37.614573 | R84: =O84*F84 -> 0 | S84: =P84*F84 -> 0 | T84: =Q84*F84 -> 0
A85: Ordering Period 4:
A86: Ordering Period 4 Labor Categories & Hours
A87: Service | B87: ID | C87: Labor Category | D87: Reference | E87: Location | F87: Hours | H87: (Floor Rate) | I87: Direct Labor (Proposed) | J87: Direct Labor (Calculation) | K87: Fringe Benefit | L87: Labor OH 1 | M87: G&A | N87: FCCOM | O87: Cost | P87: Fee | Q87: FBLR | R87: Total Cost | S87: Total Fee | T87: Total Price
A88: CONUS
A89: Program Management | B89: 001 | C89: Project Management Specialist | D89: Section H.3.1.11 | E89: CONUS | H89: =H61+(H61*Escalation!$D$4) -> 46.216875 | I89: =I61+(I61*Escalation!$D$4) -> 0 | J89: =IF($I89<$H89,$H89,$I89) -> 46.216875 | K89: =(J89*$K$4) -> 0 | L89: =(K89+J89)*$L$4 -> 0 | M89: =(K89+J89+L89)*$M$4 -> 0 | N89: =(J89+K89+L89+M89)*$N$4 -> 0 | O89: =SUM(J89:N89) -> 46.216875 | P89: =IF($P$4<0,"N/A",$P$4*(J89+K89+L89+M89)) -> 0 | Q89: =SUM(O89:P89) -> 46.216875 | R89: =O89*F89 -> 0 | S89: =P89*F89 -> 0 | T89: =Q89*F89 -> 0
A90: Field Service Representative (FSR) | B90: 002 | C90: Field Service Representative | D90: Section H.3.1.9 | E90: CONUS | H90: =H62+(H62*Escalation!$D$4) -> 32.393175 | I90: =I62+(I62*Escalation!$D$4) -> 0 | J90: =IF($I90<$H90,$H90,$I90) -> 32.393175 | K90: =(J90*$K$4) -> 0 | L90: =(K90+J90)*$L$4 -> 0 | M90: =(K90+J90+L90)*$M$4 -> 0 | N90: =(J90+K90+L90+M90)*$N$4 -> 0 | O90: =SUM(J90:N90) -> 32.393175 | P90: =IF($P$4<0,"N/A",$P$4*(J90+K90+L90+M90)) -> 0 | Q90: =SUM(O90:P90) -> 32.393175 | R90: =O90*F90 -> 0 | S90: =P90*F90 -> 0 | T90: =Q90*F90 -> 0
A91: General Maintenance | B91: 003 | C91: Heavy Equipment Mechanic | D91: Section H.3.1.3 | E91: CONUS | H91: =H63+(H63*Escalation!$D$4) -> 32.393175 | I91: =I63+(I63*Escalation!$D$4) -> 0 | J91: =IF($I91<$H91,$H91,$I91) -> 32.393175 | K91: =(J91*$K$4) -> 0 | L91: =(K91+J91)*$L$4 -> 0 | M91: =(K91+J91+L91)*$M$4 -> 0 | N91: =(J91+K91+L91+M91)*$N$4 -> 0 | O91: =SUM(J91:N91) -> 32.393175 | P91: =IF($P$4<0,"N/A",$P$4*(J91+K91+L91+M91)) -> 0 | Q91: =SUM(O91:P91) -> 32.393175 | R91: =O91*F91 -> 0 | S91: =P91*F91 -> 0 | T91: =Q91*F91 -> 0
A92: Modified Work Orders (MWO) | B92: 004 | C92: Field Service Representative | D92: Section H.3.1.9 | E92: CONUS | H92: =H64+(H64*Escalation!$D$4) -> 32.393175 | I92: =I64+(I64*Escalation!$D$4) -> 0 | J92: =IF($I92<$H92,$H92,$I92) -> 32.393175 | K92: =(J92*$K$4) -> 0 | L92: =(K92+J92)*$L$4 -> 0 | M92: =(K92+J92+L92)*$M$4 -> 0 | N92: =(J92+K92+L92+M92)*$N$4 -> 0 | O92: =SUM(J92:N92) -> 32.393175 | P92: =IF($P$4<0,"N/A",$P$4*(J92+K92+L92+M92)) -> 0 | Q92: =SUM(O92:P92) -> 32.393175 | R92: =O92*F92 -> 0 | S92: =P92*F92 -> 0 | T92: =Q92*F92 -> 0
B93: 005 | C93: Modified Work Orders (MWO) | D93: Section H.3.1.6 | E93: CONUS | H93: =H65+(H65*Escalation!$D$4) -> 32.393175 | I93: =I65+(I65*Escalation!$D$4) -> 0 | J93: =IF($I93<$H93,$H93,$I93) -> 32.393175 | K93: =(J93*$K$4) -> 0 | L93: =(K93+J93)*$L$4 -> 0 | M93: =(K93+J93+L93)*$M$4 -> 0 | N93: =(J93+K93+L93+M93)*$N$4 -> 0 | O93: =SUM(J93:N93) -> 32.393175 | P93: =IF($P$4<0,"N/A",$P$4*(J93+K93+L93+M93)) -> 0 | Q93: =SUM(O93:P93) -> 32.393175 | R93: =O93*F93 -> 0 | S93: =P93*F93 -> 0 | T93: =Q93*F93 -> 0
B94: 006 | C94: Quality Assurance | D94: Section H.3.1.10 | E94: CONUS | H94: =H66+(H66*Escalation!$D$4) -> 32.393175 | I94: =I66+(I66*Escalation!$D$4) -> 0 | J94: =IF($I94<$H94,$H94,$I94) -> 32.393175 | K94: =(J94*$K$4) -> 0 | L94: =(K94+J94)*$L$4 -> 0 | M94: =(K94+J94+L94)*$M$4 -> 0 | N94: =(J94+K94+L94+M94)*$N$4 -> 0 | O94: =SUM(J94:N94) -> 32.393175 | P94: =IF($P$4<0,"N/A",$P$4*(J94+K94+L94+M94)) -> 0 | Q94: =SUM(O94:P94) -> 32.393175 | R94: =O94*F94 -> 0 | S94: =P94*F94 -> 0 | T94: =Q94*F94 -> 0
B95: 007 | C95: Software | D95: Section H.3.1.5 | E95: CONUS | H95: =H67+(H67*Escalation!$D$4) -> 32.393175 | I95: =I67+(I67*Escalation!$D$4) -> 0 | J95: =IF($I95<$H95,$H95,$I95) -> 32.393175 | K95: =(J95*$K$4) -> 0 | L95: =(K95+J95)*$L$4 -> 0 | M95: =(K95+J95+L95)*$M$4 -> 0 | N95: =(J95+K95+L95+M95)*$N$4 -> 0 | O95: =SUM(J95:N95) -> 32.393175 | P95: =IF($P$4<0,"N/A",$P$4*(J95+K95+L95+M95)) -> 0 | Q95: =SUM(O95:P95) -> 32.393175 | R95: =O95*F95 -> 0 | S95: =P95*F95 -> 0 | T95: =Q95*F95 -> 0
B96: 008 | C96: Welder | D96: Section H.3.1.4 | E96: CONUS | H96: =H68+(H68*Escalation!$D$4) -> 25.655481 | I96: =I68+(I68*Escalation!$D$4) -> 0 | J96: =IF($I96<$H96,$H96,$I96) -> 25.655481 | K96: =(J96*$K$4) -> 0 | L96: =(K96+J96)*$L$4 -> 0 | M96: =(K96+J96+L96)*$M$4 -> 0 | N96: =(J96+K96+L96+M96)*$N$4 -> 0 | O96: =SUM(J96:N96) -> 25.655481 | P96: =IF($P$4<0,"N/A",$P$4*(J96+K96+L96+M96)) -> 0 | Q96: =SUM(O96:P96) -> 25.655481 | R96: =O96*F96 -> 0 | S96: =P96*F96 -> 0 | T96: =Q96*F96 -> 0
A97: New Equipment Training (NET) | B97: 009 | C97: Instructor Supervisor | D97: Section H.3.1.7 | E97: CONUS | H97: =H69+(H69*Escalation!$D$4) -> 27.538552 | I97: =I69+(I69*Escalation!$D$4) -> 0 | J97: =IF($I97<$H97,$H97,$I97) -> 27.538552 | K97: =(J97*$K$4) -> 0 | L97: =(K97+J97)*$L$4 -> 0 | M97: =(K97+J97+L97)*$M$4 -> 0 | N97: =(J97+K97+L97+M97)*$N$4 -> 0 | O97: =SUM(J97:N97) -> 27.538552 | P97: =IF($P$4<0,"N/A",$P$4*(J97+K97+L97+M97)) -> 0 | Q97: =SUM(O97:P97) -> 27.538552 | R97: =O97*F97 -> 0 | S97: =P97*F97 -> 0 | T97: =Q97*F97 -> 0
B98: 010 | C98: Instructor | D98: Section H.3.1.8 | E98: CONUS | H98: =H70+(H70*Escalation!$D$4) -> 27.538552 | I98: =I70+(I70*Escalation!$D$4) -> 0 | J98: =IF($I98<$H98,$H98,$I98) -> 27.538552 | K98: =(J98*$K$4) -> 0 | L98: =(K98+J98)*$L$4 -> 0 | M98: =(K98+J98+L98)*$M$4 -> 0 | N98: =(J98+K98+L98+M98)*$N$4 -> 0 | O98: =SUM(J98:N98) -> 27.538552 | P98: =IF($P$4<0,"N/A",$P$4*(J98+K98+L98+M98)) -> 0 | Q98: =SUM(O98:P98) -> 27.538552 | R98: =O98*F98 -> 0 | S98: =P98*F98 -> 0 | T98: =Q98*F98 -> 0
A99: Total Package Fielding (TPF) and De-processing | B99: 011 | C99: Heavy Equipment Mechanic | D99: Section H.3.1.3 | E99: CONUS | H99: =H71+(H71*Escalation!$D$4) -> 32.393175 | I99: =I71+(I71*Escalation!$D$4) -> 0 | J99: =IF($I99<$H99,$H99,$I99) -> 32.393175 | K99: =(J99*$K$4) -> 0 | L99: =(K99+J99)*$L$4 -> 0 | M99: =(K99+J99+L99)*$M$4 -> 0 | N99: =(J99+K99+L99+M99)*$N$4 -> 0 | O99: =SUM(J99:N99) -> 32.393175 | P99: =IF($P$4<0,"N/A",$P$4*(J99+K99+L99+M99)) -> 0 | Q99: =SUM(O99:P99) -> 32.393175 | R99: =O99*F99 -> 0 | S99: =P99*F99 -> 0 | T99: =Q99*F99 -> 0
B100: 012 | C100: Material Handling Specialist | D100: Section H.3.1.2 | E100: CONUS | H100: =H72+(H72*Escalation!$D$4) -> 28.202525 | I100: =I72+(I72*Escalation!$D$4) -> 0 | J100: =IF($I100<$H100,$H100,$I100) -> 28.202525 | K100: =(J100*$K$4) -> 0 | L100: =(K100+J100)*$L$4 -> 0 | M100: =(K100+J100+L100)*$M$4 -> 0 | N100: =(J100+K100+L100+M100)*$N$4 -> 0 | O100: =SUM(J100:N100) -> 28.202525 | P100: =IF($P$4<0,"N/A",$P$4*(J100+K100+L100+M100)) -> 0 | Q100: =SUM(O100:P100) -> 28.202525 | R100: =O100*F100 -> 0 | S100: =P100*F100 -> 0 | T100: =Q100*F100 -> 0
...

Sheet Escalation
A1: POP | B1: Minimum Escalation | C1: Proposed Escalation | D1: Calculated Escalation
A2: Ordering Period 2 | B2: 0.032 | D2: =IF($C2<$B2,$B2,$C2) -> 0.032
A3: Ordering Period 3 | B3: 0.027 | D3: =IF($C3<$B3,$B3,$C3) -> 0.027
A4: Ordering Period 4 | B4: 0.027 | D4: =IF($C4<$B4,$B4,$C4) -> 0.027
A5: Ordering Period 5 | B5: 0.027 | D5: =IF($C5<$B5,$B5,$C5) -> 0.027

Sheet Sub FBLR & DBA Summary
A1: Service | B1: ID | C1: Labor Category | D1: Reference | E1: Location | F1: Hours | G1: SUB FBLR
A2: Ordering Period 1
A3: CONUS
A4: Program Management | B4: 001 | C4: Project Management Specialist | D4: Section H.3.1.11 | E4: CONUS | F4: ='Subcontractor Labor Build'!F5 -> 0 | G4: ='Subcontractor Labor Build'!Q5 -> 42.46
A5: Field Service Representative (FSR) | B5: 002 | C5: Field Service Representative | D5: Section H.3.1.9 | E5: CONUS | F5: ='Subcontractor Labor Build'!F6 -> 0 | G5: ='Subcontractor Labor Build'!Q6 -> 29.76
A6: General Maintenance | B6: 003 | C6: Heavy Equipment Mechanic | D6: Section H.3.1.3 | E6: CONUS | F6: ='Subcontractor Labor Build'!F7 -> 0 | G6: ='Subcontractor Labor Build'!Q7 -> 29.76
A7: Modified Work Orders (MWO) | B7: 004 | C7: Field Service Representative | D7: Section H.3.1.9 | E7: CONUS | F7: ='Subcontractor Labor Build'!F8 -> 0 | G7: ='Subcontractor Labor Build'!Q8 -> 29.76
B8: 005 | C8: Modified Work Orders (MWO) | D8: Section H.3.1.6 | E8: CONUS | F8: ='Subcontractor Labor Build'!F9 -> 0 | G8: ='Subcontractor Labor Build'!Q9 -> 29.76
B9: 006 | C9: Quality Assurance | D9: Section H.3.1.10 | E9: CONUS | F9: ='Subcontractor Labor Build'!F10 -> 0 | G9: ='Subcontractor Labor Build'!Q10 -> 29.76 | K9: DBA Insurance Totals
B10: 007 | C10: Software | D10: Section H.3.1.5 | E10: CONUS | F10: ='Subcontractor Labor Build'!F11 -> 0 | G10: ='Subcontractor Labor Build'!Q11 -> 29.76
B11: 008 | C11: Welder | D11: Section H.3.1.4 | E11: CONUS | F11: ='Subcontractor Labor Build'!F12 -> 0 | G11: ='Subcontractor Labor Build'!Q12 -> 23.57 | K11: Base - DBA Total | M11: 0
A12: New Equipment Training (NET) | B12: 009 | C12: Instructor Supervisor | D12: Section H.3.1.7 | E12: CONUS | F12: ='Subcontractor Labor Build'!F13 -> 0 | G12: ='Subcontractor Labor Build'!Q13 -> 25.3 | K12: Option 1 - DBA Total | M12: 0
B13: 010 | C13: Instructor | D13: Section H.3.1.8 | E13: CONUS | F13: ='Subcontractor Labor Build'!F14 -> 0 | G13: ='Subcontractor Labor Build'!Q14 -> 25.3 | K13: Option 2 - DBA Total | M13: 0
A14: Total Package Fielding (TPF) and De-processing | B14: 011 | C14: Heavy Equipment Mechanic | D14: Section H.3.1.3 | E14: CONUS | F14: ='Subcontractor Labor Build'!F15 -> 0 | G14: ='Subcontractor Labor Build'!Q15 -> 29.76 | K14: Option 3 - DBA Total | M14: 0
B15: 012 | C15: Material Handling Specialist | D15: Section H.3.1.2 | E15: CONUS | F15: ='Subcontractor Labor Build'!F16 -> 0 | G15: ='Subcontractor Labor Build'!Q16 -> 25.91 | K15: Option 4 - DBA Total | M15: 0
B16: 013 | C16: Quality Assurance | D16: Section H.3.1.10 | E16: CONUS | F16: ='Subcontractor Labor Build'!F17 -> 0 | G16: ='Subcontractor Labor Build'!Q17 -> 29.76 | K16: Dash 8 - DBA Total | M16: =M15*0.5 -> 0
B17: 014 | C17: Supply/Procurement Specialist | D17: Section H.3.1.1 | E17: CONUS | F17: ='Subcontractor Labor Build'!F18 -> 0 | G17: ='Subcontractor Labor Build'!Q18 -> 33.8
B18: 015 | C18: Welder | D18: Section H.3.1.4 | E18: CONUS | F18: ='Subcontractor Labor Build'!F19 -> 0 | G18: ='Subcontractor Labor Build'!Q19 -> 23.57 | K18: Total Subcontractor DBA | M18: =M11+M12+M13+M14+M15+M16 -> 0
A19: OCONUS
A20: Field Service Representative (FSR) | B20: 016 | C20: Field Service Representative | E20: OCONUS | F20: ='Subcontractor Labor Build'!F21 -> 0 | G20: ='Subcontractor Labor Build'!Q21 -> 31.25
A21: General Maintenance | B21: 017 | C21: Heavy Equipment Mechanic | E21: OCONUS | F21: ='Subcontractor Labor Build'!F22 -> 0 | G21: ='Subcontractor Labor Build'!Q22 -> 31.25
A22: New Equipment Training (NET) | B22: 018 | C22: Instructor Supervisor | E22: OCONUS | F22: ='Subcontractor Labor Build'!F23 -> 0 | G22: ='Subcontractor Labor Build'!Q23 -> 26.57
B23: 019 | C23: Instructor | E23: OCONUS | F23: ='Subcontractor Labor Build'!F24 -> 0 | G23: ='Subcontractor Labor Build'!Q24 -> 26.57
A24: Total Package Fielding (TPF) and De-processing | B24: 020 | C24: Heavy Equipment Mechanic | E24: OCONUS | F24: ='Subcontractor Labor Build'!F25 -> 0 | G24: ='Subcontractor Labor Build'!Q25 -> 31.25
B25: 021 | C25: Material Handling Specialist | E25: OCONUS | F25: ='Subcontractor Labor Build'!F26 -> 0 | G25: ='Subcontractor Labor Build'!Q26 -> 27.21
B26: 022 | C26: Quality Assurance | E26: OCONUS | F26: ='Subcontractor Labor Build'!F27 -> 0 | G26: ='Subcontractor Labor Build'!Q27 -> 31.25
B27: 023 | C27: Supply/Procurement Specialist | E27: OCONUS | F27: ='Subcontractor Labor Build'!F28 -> 0 | G27: ='Subcontractor Labor Build'!Q28 -> 35.49
A28: Ordering Period 2
A29: CONUS
A30: Program Management | B30: 001 | C30: Project Management Specialist | D30: Section H.3.1.11 | E30: CONUS | F30: ='Subcontractor Labor Build'!F33 -> 0 | G30: ='Subcontractor Labor Build'!Q33 -> 43.81872
A31: Field Service Representative (FSR) | B31: 002 | C31: Field Service Representative | D31: Section H.3.1.9 | E31: CONUS | F31: ='Subcontractor Labor Build'!F34 -> 0 | G31: ='Subcontractor Labor Build'!Q34 -> 30.71232
A32: General Maintenance | B32: 003 | C32: Heavy Equipment Mechanic | D32: Section H.3.1.3 | E32: CONUS | F32: ='Subcontractor Labor Build'!F35 -> 0 | G32: ='Subcontractor Labor Build'!Q35 -> 30.71232
A33: Modified Work Orders (MWO) | B33: 004 | C33: Field Service Representative | D33: Section H.3.1.9 | E33: CONUS | F33: ='Subcontractor Labor Build'!F36 -> 0 | G33: ='Subcontractor Labor Build'!Q36 -> 30.71232
B34: 005 | C34: Modified Work Orders (MWO) | D34: Section H.3.1.6 | E34: CONUS | F34: ='Subcontractor Labor Build'!F37 -> 0 | G34: ='Subcontractor Labor Build'!Q37 -> 30.71232
B35: 006 | C35: Quality Assurance | D35: Section H.3.1.10 | E35: CONUS | F35: ='Subcontractor Labor Build'!F38 -> 0 | G35: ='Subcontractor Labor Build'!Q38 -> 30.71232
B36: 007 | C36: Software | D36: Section H.3.1.5 | E36: CONUS | F36: ='Subcontractor Labor Build'!F39 -> 0 | G36: ='Subcontractor Labor Build'!Q39 -> 30.71232
B37: 008 | C37: Welder | D37: Section H.3.1.4 | E37: CONUS | F37: ='Subcontractor Labor Build'!F40 -> 0 | G37: ='Subcontractor Labor Build'!Q40 -> 24.32424
A38: New Equipment Training (NET) | B38: 009 | C38: Instructor Supervisor | D38: Section H.3.1.7 | E38: CONUS | F38: ='Subcontractor Labor Build'!F41 -> 0 | G38: ='Subcontractor Labor Build'!Q41 -> 26.1096
B39: 010 | C39: Instructor | D39: Section H.3.1.8 | E39: CONUS | F39: ='Subcontractor Labor Build'!F42 -> 0 | G39: ='Subcontractor Labor Build'!Q42 -> 26.1096
A40: Total Package Fielding (TPF) and De-processing | B40: 011 | C40: Heavy Equipment Mechanic | D40: Section H.3.1.3 | E40: CONUS | F40: ='Subcontractor Labor Build'!F43 -> 0 | G40: ='Subcontractor Labor Build'!Q43 -> 30.71232
B41: 012 | C41: Material Handling Specialist | D41: Section H.3.1.2 | E41: CONUS | F41: ='Subcontractor Labor Build'!F44 -> 0 | G41: ='Subcontractor Labor Build'!Q44 -> 26.73912
B42: 013 | C42: Quality Assurance | D42: Section H.3.1.10 | E42: CONUS | F42: ='Subcontractor Labor Build'!F45 -> 0 | G42: ='Subcontractor Labor Build'!Q45 -> 30.71232
B43: 014 | C43: Supply/Procurement Specialist | D43: Section H.3.1.1 | E43: CONUS | F43: ='Subcontractor Labor Build'!F46 -> 0 | G43: ='Subcontractor Labor Build'!Q46 -> 34.8816
B44: 015 | C44: Welder | D44: Section H.3.1.4 | E44: CONUS | F44: ='Subcontractor Labor Build'!F47 -> 0 | G44: ='Subcontractor Labor Build'!Q47 -> 24.32424
A45: OCONUS
A46: Field Service Representative (FSR) | B46: 016 | C46: Field Service Representative | E46: OCONUS | F46: ='Subcontractor Labor Build'!F49 -> 0 | G46: ='Subcontractor Labor Build'!Q49 -> 32.25
A47: General Maintenance | B47: 017 | C47: Heavy Equipment Mechanic | E47: OCONUS | F47: ='Subcontractor Labor Build'!F50 -> 0 | G47: ='Subcontractor Labor Build'!Q50 -> 32.25
A48: New Equipment Training (NET) | B48: 018 | C48: Instructor Supervisor | E48: OCONUS | F48: ='Subcontractor Labor Build'!F51 -> 0 | G48: ='Subcontractor Labor Build'!Q51 -> 27.42024
B49: 019 | C49: Instructor | E49: OCONUS | F49: ='Subcontractor Labor Build'!F52 -> 0 | G49: ='Subcontractor Labor Build'!Q52 -> 27.42024
A50: Total Package Fielding (TPF) and De-processing | B50: 020 | C50: Heavy Equipment Mechanic | E50: OCONUS | F50: ='Subcontractor Labor Build'!F53 -> 0 | G50: ='Subcontractor Labor Build'!Q53 -> 32.25
B51: 021 | C51: Material Handling Specialist | E51: OCONUS | F51: ='Subcontractor Labor Build'!F54 -> 0 | G51: ='Subcontractor Labor Build'!Q54 -> 28.08072
B52: 022 | C52: Quality Assurance | E52: OCONUS | F52: ='Subcontractor Labor Build'!F55 -> 0 | G52: ='Subcontractor Labor Build'!Q55 -> 32.25
B53: 023 | C53: Supply/Procurement Specialist | E53: OCONUS | F53: ='Subcontractor Labor Build'!F56 -> 0 | G53: ='Subcontractor Labor Build'!Q56 -> 36.62568
A54: Ordering Period 3
A55: CONUS
A56: Program Management | B56: 001 | C56: Project Management Specialist | D56: Section H.3.1.11 | E56: CONUS | F56: ='Subcontractor Labor Build'!F61 -> 0 | G56: ='Subcontractor Labor Build'!Q61 -> 45.001825
A57: Field Service Representative (FSR) | B57: 002 | C57: Field Service Representative | D57: Section H.3.1.9 | E57: CONUS | F57: ='Subcontractor Labor Build'!F62 -> 0 | G57: ='Subcontractor Labor Build'!Q62 -> 31.541553
A58: General Maintenance | B58: 003 | C58: Heavy Equipment Mechanic | D58: Section H.3.1.3 | E58: CONUS | F58: ='Subcontractor Labor Build'!F63 -> 0 | G58: ='Subcontractor Labor Build'!Q63 -> 31.541553
A59: Modified Work Orders (MWO) | B59: 004 | C59: Field Service Representative | D59: Section H.3.1.9 | E59: CONUS | F59: ='Subcontractor Labor Build'!F64 -> 0 | G59: ='Subcontractor Labor Build'!Q64 -> 31.541553
B60: 005 | C60: Modified Work Orders (MWO) | D60: Section H.3.1.6 | E60: CONUS | F60: ='Subcontractor Labor Build'!F65 -> 0 | G60: ='Subcontractor Labor Build'!Q65 -> 31.541553
B61: 006 | C61: Quality Assurance | D61: Section H.3.1.10 | E61: CONUS | F61: ='Subcontractor Labor Build'!F66 -> 0 | G61: ='Subcontractor Labor Build'!Q66 -> 31.541553
B62: 007 | C62: Software | D62: Section H.3.1.5 | E62: CONUS | F62: ='Subcontractor Labor Build'!F67 -> 0 | G62: ='Subcontractor Labor Build'!Q67 -> 31.541553
B63: 008 | C63: Welder | D63: Section H.3.1.4 | E63: CONUS | F63: ='Subcontractor Labor Build'!F68 -> 0 | G63: ='Subcontractor Labor Build'!Q68 -> 24.980994
A64: New Equipment Training (NET) | B64: 009 | C64: Instructor Supervisor | D64: Section H.3.1.7 | E64: CONUS | F64: ='Subcontractor Labor Build'!F69 -> 0 | G64: ='Subcontractor Labor Build'!Q69 -> 26.814559
B65: 010 | C65: Instructor | D65: Section H.3.1.8 | E65: CONUS | F65: ='Subcontractor Labor Build'!F70 -> 0 | G65: ='Subcontractor Labor Build'!Q70 -> 26.814559
A66: Total Package Fielding (TPF) and De-processing | B66: 011 | C66: Heavy Equipment Mechanic | D66: Section H.3.1.3 | E66: CONUS | F66: ='Subcontractor Labor Build'!F71 -> 0 | G66: ='Subcontractor Labor Build'!Q71 -> 31.541553
B67: 012 | C67: Material Handling Specialist | D67: Section H.3.1.2 | E67: CONUS | F67: ='Subcontractor Labor Build'!F72 -> 0 | G67: ='Subcontractor Labor Build'!Q72 -> 27.461076
B68: 013 | C68: Quality Assurance | D68: Section H.3.1.10 | E68: CONUS | F68: ='Subcontractor Labor Build'!F73 -> 0 | G68: ='Subcontractor Labor Build'!Q73 -> 31.541553
B69: 014 | C69: Supply/Procurement Specialist | D69: Section H.3.1.1 | E69: CONUS | F69: ='Subcontractor Labor Build'!F74 -> 0 | G69: ='Subcontractor Labor Build'!Q74 -> 35.823403
B70: 015 | C70: Welder | D70: Section H.3.1.4 | E70: CONUS | F70: ='Subcontractor Labor Build'!F75 -> 0 | G70: ='Subcontractor Labor Build'!Q75 -> 24.980994
A71: OCONUS
A72: Field Service Representative (FSR) | B72: 016 | C72: Field Service Representative | E72: OCONUS | F72: ='Subcontractor Labor Build'!F77 -> 0 | G72: ='Subcontractor Labor Build'!Q77 -> 33.12075
A73: General Maintenance | B73: 017 | C73: Heavy Equipment Mechanic | E73: OCONUS | F73: ='Subcontractor Labor Build'!F78 -> 0 | G73: ='Subcontractor Labor Build'!Q78 -> 33.12075
A74: New Equipment Training (NET) | B74: 018 | C74: Instructor Supervisor | E74: OCONUS | F74: ='Subcontractor Labor Build'!F79 -> 0 | G74: ='Subcontractor Labor Build'!Q79 -> 28.160586
B75: 019 | C75: Instructor | E75: OCONUS | F75: ='Subcontractor Labor Build'!F80 -> 0 | G75: ='Subcontractor Labor Build'!Q80 -> 28.160586
A76: Total Package Fielding (TPF) and De-processing | B76: 020 | C76: Heavy Equipment Mechanic | E76: OCONUS | F76: ='Subcontractor Labor Build'!F81 -> 0 | G76: ='Subcontractor Labor Build'!Q81 -> 33.12075
B77: 021 | C77: Material Handling Specialist | E77: OCONUS | F77: ='Subcontractor Labor Build'!F82 -> 0 | G77: ='Subcontractor Labor Build'!Q82 -> 28.838899
B78: 022 | C78: Quality Assurance | E78: OCONUS | F78: ='Subcontractor Labor Build'!F83 -> 0 | G78: ='Subcontractor Labor Build'!Q83 -> 33.12075
B79: 023 | C79: Supply/Procurement Specialist | E79: OCONUS | F79: ='Subcontractor Labor Build'!F84 -> 0 | G79: ='Subcontractor Labor Build'!Q84 -> 37.614573
A80: Ordering Period 4
A81: CONUS
A82: Program Management | B82: 001 | C82: Project Management Specialist | D82: Section H.3.1.11 | E82: CONUS | F82: ='Subcontractor Labor Build'!F89 -> 0 | G82: ='Subcontractor Labor Build'!Q89 -> 46.216875
A83: Field Service Representative (FSR) | B83: 002 | C83: Field Service Representative | D83: Section H.3.1.9 | E83: CONUS | F83: ='Subcontractor Labor Build'!F90 -> 0 | G83: ='Subcontractor Labor Build'!Q90 -> 32.393175
A84: General Maintenance | B84: 003 | C84: Heavy Equipment Mechanic | D84: Section H.3.1.3 | E84: CONUS | F84: ='Subcontractor Labor Build'!F91 -> 0 | G84: ='Subcontractor Labor Build'!Q91 -> 32.393175
A85: Modified Work Orders (MWO) | B85: 004 | C85: Field Service Representative | D85: Section H.3.1.9 | E85: CONUS | F85: ='Subcontractor Labor Build'!F92 -> 0 | G85: ='Subcontractor Labor Build'!Q92 -> 32.393175
B86: 005 | C86: Modified Work Orders (MWO) | D86: Section H.3.1.6 | E86: CONUS | F86: ='Subcontractor Labor Build'!F93 -> 0 | G86: ='Subcontractor Labor Build'!Q93 -> 32.393175
B87: 006 | C87: Quality Assurance | D87: Section H.3.1.10 | E87: CONUS | F87: ='Subcontractor Labor Build'!F94 -> 0 | G87: ='Subcontractor Labor Build'!Q94 -> 32.393175
B88: 007 | C88: Software | D88: Section H.3.1.5 | E88: CONUS | F88: ='Subcontractor Labor Build'!F95 -> 0 | G88: ='Subcontractor Labor Build'!Q95 -> 32.393175
B89: 008 | C89: Welder | D89: Section H.3.1.4 | E89: CONUS | F89: ='Subcontractor Labor Build'!F96 -> 0 | G89: ='Subcontractor Labor Build'!Q96 -> 25.655481
A90: New Equipment Training (NET) | B90: 009 | C90: Instructor Supervisor | D90: Section H.3.1.7 | E90: CONUS | F90: ='Subcontractor Labor Build'!F97 -> 0 | G90: ='Subcontractor Labor Build'!Q97 -> 27.538552
B91: 010 | C91: Instructor | D91: Section H.3.1.8 | E91: CONUS | F91: ='Subcontractor Labor Build'!F98 -> 0 | G91: ='Subcontractor Labor Build'!Q98 -> 27.538552
A92: Total Package Fielding (TPF) and De-processing | B92: 011 | C92: Heavy Equipment Mechanic | D92: Section H.3.1.3 | E92: CONUS | F92: ='Subcontractor Labor Build'!F99 -> 0 | G92: ='Subcontractor Labor Build'!Q99 -> 32.393175
B93: 012 | C93: Material Handling Specialist | D93: Section H.3.1.2 | E93: CONUS | F93: ='Subcontractor Labor Build'!F100 -> 0 | G93: ='Subcontractor Labor Build'!Q100 -> 28.202525
B94: 013 | C94: Quality Assurance | D94: Section H.3.1.10 | E94: CONUS | F94: ='Subcontractor Labor Build'!F101 -> 0 | G94: ='Subcontractor Labor Build'!Q101 -> 32.393175
B95: 014 | C95: Supply/Procurement Specialist | D95: Section H.3.1.1 | E95: CONUS | F95: ='Subcontractor Labor Build'!F102 -> 0 | G95: ='Subcontractor Labor Build'!Q102 -> 36.790635
B96: 015 | C96: Welder | D96: Section H.3.1.4 | E96: CONUS | F96: ='Subcontractor Labor Build'!F103 -> 0 | G96: ='Subcontractor Labor Build'!Q103 -> 25.655481
A97: OCONUS
A98: Field Service Representative (FSR) | B98: 016 | C98: Field Service Representative | E98: OCONUS | F98: ='Subcontractor Labor Build'!F105 -> 0 | G98: ='Subcontractor Labor Build'!Q105 -> 34.01501
A99: General Maintenance | B99: 017 | C99: Heavy Equipment Mechanic | E99: OCONUS | F99: ='Subcontractor Labor Build'!F106 -> 0 | G99: ='Subcontractor Labor Build'!Q106 -> 34.01501
A100: Total Package Fielding (TPF) and De-processing | B100: 020 | C100: Heavy Equipment Mechanic | E100: OCONUS | F100: ='Subcontractor Labor Build'!F107 -> 0 | G100: ='Subcontractor Labor Build'!Q107 -> 34.01501
...

Sheet DBA Insurance
A1: Subcontractors shall use this tab to demonstrate how the estimated DBA Insurance costs were calculated, if applicable.
